Workbook

Sheet Guide
A1: English words and clues for Granny's Puzzle
A3: What's here
A4: Every English word the game can use, one sheet per length, easiest first. The words, difficulties and definitions came from SCOWL and WordNet (free word lists); the clues already written are filled in. This file is now the record: the importer builds the game's word list from it.
A6: What to do
A7: Write clues in Clue 1 to 3. Start with Easy, then Medium: those are the words levels use. A word with no clue is fine; it waits until it gets one.
A8: To add a word, write it in an empty row at the bottom of its length's sheet, lowercase, with a difficulty. To remove a word, delete its whole row.
A9: Use the filter arrows in the header row to show, for example, only Easy words with an empty Clue 1.
A11: Columns
A12: Difficulty: Easy = everyone knows it. Medium = normal adult vocabulary. Hard = less common. Rare = unusual, crossword-veteran words; change any you disagree with.
A13: Definition (grey): what the word means, from WordNet, as a help. Not shown in the game. Check it: WordNet sometimes lists a less common meaning first.
A14: The beige columns (ID, Letters, Len) fill themselves.
A16: Clue rules (CLUE_STYLE.md has them all)
... A25: Word: card · Difficulty: Easy · Clue 1: Credit ___ · Clue 2: Birthday greeting · Clue 3: Deck member

Sheet Summary
A1: Sheet | B1: Words | C1: With a clue | D1: Easy | E1: Medium | F1: Hard | G1: Rare | H1: Easy + Medium still to clue
A2: 2 letters | B2: =COUNTA('2 letters'!B2:B529) -> 28 | C2: =COUNTIFS('2 letters'!B2:B529,"<>",'2 letters'!F2:F529,"<>") -> 22 | D2: =COUNTIF('2 letters'!D2:D529,"Easy") -> 21 | E2: =COUNTIF('2 letters'!D2:D529,"Medium") -> 2 | F2: =COUNTIF('2 letters'!D2:D529,"Hard") -> 4 | G2: =COUNTIF('2 letters'!D2:D529,"Rare") -> 1 | H2: =COUNTIFS('2 letters'!D2:D529,"Easy",'2 letters'!F2:F529,"")+COUNTIFS('2 letters'!D2:D529,"Medium",'2 letters'!F2:F529,"") -> 1
A3: 3 letters | B3: =COUNTA('3 letters'!B2:B929) -> 428 | C3: =COUNTIFS('3 letters'!B2:B929,"<>",'3 letters'!F2:F929,"<>") -> 147 | D3: =COUNTIF('3 letters'!D2:D929,"Easy") -> 127 | E3: =COUNTIF('3 letters'!D2:D929,"Medium") -> 97 | F3: =COUNTIF('3 letters'!D2:D929,"Hard") -> 171 | G3: =COUNTIF('3 letters'!D2:D929,"Rare") -> 33 | H3: =COUNTIFS('3 letters'!D2:D929,"Easy",'3 letters'!F2:F929,"")+COUNTIFS('3 letters'!D2:D929,"Medium",'3 letters'!F2:F929,"") -> 77
A4: 4 letters | B4: =COUNTA('4 letters'!B2:B1959) -> 1458 | C4: =COUNTIFS('4 letters'!B2:B1959,"<>",'4 letters'!F2:F1959,"<>") -> 211 | D4: =COUNTIF('4 letters'!D2:D1959,"Easy") -> 363 | E4: =COUNTIF('4 letters'!D2:D1959,"Medium") -> 342 | F4: =COUNTIF('4 letters'!D2:D1959,"Hard") -> 603 | G4: =COUNTIF('4 letters'!D2:D1959,"Rare") -> 150 | H4: =COUNTIFS('4 letters'!D2:D1959,"Easy",'4 letters'!F2:F1959,"")+COUNTIFS('4 letters'!D2:D1959,"Medium",'4 letters'!F2:F1959,"") -> 494
A5: 5 letters | B5: =COUNTA('5 letters'!B2:B2559) -> 2058 | C5: =COUNTIFS('5 letters'!B2:B2559,"<>",'5 letters'!F2:F2559,"<>") -> 178 | D5: =COUNTIF('5 letters'!D2:D2559,"Easy") -> 367 | E5: =COUNTIF('5 letters'!D2:D2559,"Medium") -> 410 | F5: =COUNTIF('5 letters'!D2:D2559,"Hard") -> 989 | G5: =COUNTIF('5 letters'!D2:D2559,"Rare") -> 292 | H5: =COUNTIFS('5 letters'!D2:D2559,"Easy",'5 letters'!F2:F2559,"")+COUNTIFS('5 letters'!D2:D2559,"Medium",'5 letters'!F2:F2559,"") -> 599
A6: 6 letters | B6: =COUNTA('6 letters'!B2:B3183) -> 2682 | C6: =COUNTIFS('6 letters'!B2:B3183,"<>",'6 letters'!F2:F3183,"<>") -> 159 | D6: =COUNTIF('6 letters'!D2:D3183,"Easy") -> 352 | E6: =COUNTIF('6 letters'!D2:D3183,"Medium") -> 458 | F6: =COUNTIF('6 letters'!D2:D3183,"Hard") -> 1433 | G6: =COUNTIF('6 letters'!D2:D3183,"Rare") -> 439 | H6: =COUNTIFS('6 letters'!D2:D3183,"Easy",'6 letters'!F2:F3183,"")+COUNTIFS('6 letters'!D2:D3183,"Medium",'6 letters'!F2:F3183,"") -> 651
A7: 7 letters | B7: =COUNTA('7 letters'!B2:B3502) -> 3001 | C7: =COUNTIFS('7 letters'!B2:B3502,"<>",'7 letters'!F2:F3502,"<>") -> 0 | D7: =COUNTIF('7 letters'!D2:D3502,"Easy") -> 359 | E7: =COUNTIF('7 letters'!D2:D3502,"Medium") -> 540 | F7: =COUNTIF('7 letters'!D2:D3502,"Hard") -> 1520 | G7: =COUNTIF('7 letters'!D2:D3502,"Rare") -> 582 | H7: =COUNTIFS('7 letters'!D2:D3502,"Easy",'7 letters'!F2:F3502,"")+COUNTIFS('7 letters'!D2:D3502,"Medium",'7 letters'!F2:F3502,"") -> 899
A8: 8 letters | B8: =COUNTA('8 letters'!B2:B3346) -> 2845 | C8: =COUNTIFS('8 letters'!B2:B3346,"<>",'8 letters'!F2:F3346,"<>") -> 0 | D8: =COUNTIF('8 letters'!D2:D3346,"Easy") -> 274 | E8: =COUNTIF('8 letters'!D2:D3346,"Medium") -> 483 | F8: =COUNTIF('8 letters'!D2:D3346,"Hard") -> 1419 | G8: =COUNTIF('8 letters'!D2:D3346,"Rare") -> 669 | H8: =COUNTIFS('8 letters'!D2:D3346,"Easy",'8 letters'!F2:F3346,"")+COUNTIFS('8 letters'!D2:D3346,"Medium",'8 letters'!F2:F3346,"") -> 757
A9: Total | B9: =SUM(B2:B8) -> 12500 | C9: =SUM(C2:C8) -> 717 | D9: =SUM(D2:D8) -> 1863 | E9: =SUM(E2:E8) -> 2332 | F9: =SUM(F2:F8) -> 6139 | G9: =SUM(G2:G8) -> 2166 | H9: =SUM(H2:H8) -> 3478
A11: Levels use Easy and Medium words by default (the generator's familiarity cut-off is 20), so the last column is the clue work that matters first. Hard and Rare words only appear if a pack is generated with a higher cut-off.

Sheet 2 letters
A1: ID | B1: Word | C1: Letters | D1: Difficulty | E1: Definition | F1: Clue 1 | G1: Len | H1: Clue 2 | I1: Len | J1: Clue 3 | K1: Len | L1: Notes
A2: =IF(B2="","",ROW()-1) -> 1 | B2: am | C2: =IF(B2="","",LEN(TRIM(B2))) -> 2 | D2: Easy | E2: a radioactive transuranic metallic element | F2: I ___ ready | G2: =IF(F2="","",LEN(F2)) -> 11 | H2: I ___ here | I2: =IF(H2="","",LEN(H2)) -> 10 | K2: =IF(J2="","",LEN(J2))
A3: =IF(B3="","",ROW()-1) -> 2 | B3: an | C3: =IF(B3="","",LEN(TRIM(B3))) -> 2 | D3: Easy | E3: an associate degree in nursing | F3: ___ apple a day | G3: =IF(F3="","",LEN(F3)) -> 15 | H3: ___ hour ago | I3: =IF(H3="","",LEN(H3)) -> 12 | K3: =IF(J3="","",LEN(J3))
A4: =IF(B4="","",ROW()-1) -> 3 | B4: as | C4: =IF(B4="","",LEN(TRIM(B4))) -> 2 | D4: Easy | E4: to the same degree (often followed by `as') | F4: Just ___ good | G4: =IF(F4="","",LEN(F4)) -> 13 | H4: Same ___ before | I4: =IF(H4="","",LEN(H4)) -> 15 | K4: =IF(J4="","",LEN(J4))
A5: =IF(B5="","",ROW()-1) -> 4 | B5: at | C5: =IF(B5="","",LEN(TRIM(B5))) -> 2 | D5: Easy | E5: a highly unstable radioactive element (the heaviest of the halogen series) | F5: Meet ___ noon | G5: =IF(F5="","",LEN(F5)) -> 13 | H5: Located in | I5: =IF(H5="","",LEN(H5)) -> 10 | K5: =IF(J5="","",LEN(J5))
A6: =IF(B6="","",ROW()-1) -> 5 | B6: be | C6: =IF(B6="","",LEN(TRIM(B6))) -> 2 | D6: Easy | E6: have the quality of being | F6: To ___ or not to ___ | G6: =IF(F6="","",LEN(F6)) -> 20 | H6: Exist | I6: =IF(H6="","",LEN(H6)) -> 5 | K6: =IF(J6="","",LEN(J6))
A7: =IF(B7="","",ROW()-1) -> 6 | B7: by | C7: =IF(B7="","",LEN(TRIM(B7))) -> 2 | D7: Easy | E7: so as to pass a given point | F7: Next to | G7: =IF(F7="","",LEN(F7)) -> 7 | H7: Close ___ | I7: =IF(H7="","",LEN(H7)) -> 9 | K7: =IF(J7="","",LEN(J7))
A8: =IF(B8="","",ROW()-1) -> 7 | B8: do | C8: =IF(B8="","",LEN(TRIM(B8))) -> 2 | D8: Easy | E8: engage in | F8: Perform | G8: =IF(F8="","",LEN(F8)) -> 7 | H8: To-___ list | I8: =IF(H8="","",LEN(H8)) -> 11 | K8: =IF(J8="","",LEN(J8))
A9: =IF(B9="","",ROW()-1) -> 8 | B9: go | C9: =IF(B9="","",LEN(TRIM(B9))) -> 2 | D9: Easy | E9: change location | F9: Leave | G9: =IF(F9="","",LEN(F9)) -> 5 | H9: Green light word | I9: =IF(H9="","",LEN(H9)) -> 16 | K9: =IF(J9="","",LEN(J9))
A10: =IF(B10="","",ROW()-1) -> 9 | B10: he | C10: =IF(B10="","",LEN(TRIM(B10))) -> 2 | D10: Easy | E10: a very light colorless element that is one of the six inert gasses | F10: That man | G10: =IF(F10="","",LEN(F10)) -> 8 | H10: Him, as subject | I10: =IF(H10="","",LEN(H10)) -> 15 | K10: =IF(J10="","",LEN(J10))
A11: =IF(B11="","",ROW()-1) -> 10 | B11: in | C11: =IF(B11="","",LEN(TRIM(B11))) -> 2 | D11: Easy | E11: a unit of length equal to one twelfth of a foot | F11: Not out | G11: =IF(F11="","",LEN(F11)) -> 7 | H11: Trendy | I11: =IF(H11="","",LEN(H11)) -> 6 | K11: =IF(J11="","",LEN(J11))
A12: =IF(B12="","",ROW()-1) -> 11 | B12: it | C12: =IF(B12="","",LEN(TRIM(B12))) -> 2 | D12: Easy | E12: the branch of engineering that deals with the use of computers and telecommunications to retrieve and store and transmit information | F12: Tag player | G12: =IF(F12="","",LEN(F12)) -> 10 | H12: That thing | I12: =IF(H12="","",LEN(H12)) -> 10 | K12: =IF(J12="","",LEN(J12))
A13: =IF(B13="","",ROW()-1) -> 12 | B13: me | C13: =IF(B13="","",LEN(TRIM(B13))) -> 2 | D13: Easy | E13: a state in New England | F13: Myself | G13: =IF(F13="","",LEN(F13)) -> 6 | H13: Not you | I13: =IF(H13="","",LEN(H13)) -> 7 | K13: =IF(J13="","",LEN(J13))
... A22: =IF(B22="","",ROW()-1) -> 21 | B22: us | C22: =IF(B22="","",LEN(TRIM(B22))) -> 2 | D22: Easy | E22: North American republic containing 50 states - 48 conterminous states in North America plus Alaska in northwest North America and the Hawaiian Islands in the Pacific Ocean | F22: You and me | G22: =IF(F22="","",LEN(F22)) -> 10 | H22: We, as object | I22: =IF(H22="","",LEN(H22)) -> 13 | K22: =IF(J22="","",LEN(J22))
A23: =IF(B23="","",ROW()-1) -> 22 | B23: ax | C23: =IF(B23="","",LEN(TRIM(B23))) -> 2 | D23: Medium | E23: an edge tool with a heavy bladed head mounted across a handle | G23: =IF(F23="","",LEN(F23)) | I23: =IF(H23="","",LEN(H23)) | K23: =IF(J23="","",LEN(J23))
A24: =IF(B24="","",ROW()-1) -> 23 | B24: ha | C24: =IF(B24="","",LEN(TRIM(B24))) -> 2 | D24: Medium | E24: (astronomy) the angular distance of a celestial point measured westward along the celestial equator from the zenith crossing | F24: Laugh sound | G24: =IF(F24="","",LEN(F24)) -> 11 | H24: Gotcha! | I24: =IF(H24="","",LEN(H24)) -> 7 | K24: =IF(J24="","",LEN(J24))
A25: =IF(B25="","",ROW()-1) -> 24 | B25: ad | C25: =IF(B25="","",LEN(TRIM(B25))) -> 2 | D25: Hard | E25: a public promotion of some product or service | G25: =IF(F25="","",LEN(F25)) | I25: =IF(H25="","",LEN(H25)) | K25: =IF(J25="","",LEN(J25))
A26: =IF(B26="","",ROW()-1) -> 25 | B26: hi | C26: =IF(B26="","",LEN(TRIM(B26))) -> 2 | D26: Hard | E26: an expression of greeting | G26: =IF(F26="","",LEN(F26)) | I26: =IF(H26="","",LEN(H26)) | K26: =IF(J26="","",LEN(J26))
A27: =IF(B27="","",ROW()-1) -> 26 | B27: ox | C27: =IF(B27="","",LEN(TRIM(B27))) -> 2 | D27: Hard | E27: an adult castrated bull of the genus Bos | G27: =IF(F27="","",LEN(F27)) | I27: =IF(H27="","",LEN(H27)) | K27: =IF(J27="","",LEN(J27))
A28: =IF(B28="","",ROW()-1) -> 27 | B28: pa | C28: =IF(B28="","",LEN(TRIM(B28))) -> 2 | D28: Hard | E28: an informal term for a father | G28: =IF(F28="","",LEN(F28)) | I28: =IF(H28="","",LEN(H28)) | K28: =IF(J28="","",LEN(J28))
A29: =IF(B29="","",ROW()-1) -> 28 | B29: ex | C29: =IF(B29="","",LEN(TRIM(B29))) -> 2 | D29: Rare | E29: a man who was formerly a certain woman's husband | G29: =IF(F29="","",LEN(F29)) | I29: =IF(H29="","",LEN(H29)) | K29: =IF(J29="","",LEN(J29))
A30: =IF(B30="","",ROW()-1) | C30: =IF(B30="","",LEN(TRIM(B30))) | G30: =IF(F30="","",LEN(F30)) | I30: =IF(H30="","",LEN(H30)) | K30: =IF(J30="","",LEN(J30))
A31: =IF(B31="","",ROW()-1) | C31: =IF(B31="","",LEN(TRIM(B31))) | G31: =IF(F31="","",LEN(F31)) | I31: =IF(H31="","",LEN(H31)) | K31: =IF(J31="","",LEN(J31))
A32: =IF(B32="","",ROW()-1) | C32: =IF(B32="","",LEN(TRIM(B32))) | G32: =IF(F32="","",LEN(F32)) | I32: =IF(H32="","",LEN(H32)) | K32: =IF(J32="","",LEN(J32))
A33: =IF(B33="","",ROW()-1) | C33: =IF(B33="","",LEN(TRIM(B33))) | G33: =IF(F33="","",LEN(F33)) | I33: =IF(H33="","",LEN(H33)) | K33: =IF(J33="","",LEN(J33))
A34: =IF(B34="","",ROW()-1) | C34: =IF(B34="","",LEN(TRIM(B34))) | G34: =IF(F34="","",LEN(F34)) | I34: =IF(H34="","",LEN(H34)) | K34: =IF(J34="","",LEN(J34))
A35: =IF(B35="","",ROW()-1) | C35: =IF(B35="","",LEN(TRIM(B35))) | G35: =IF(F35="","",LEN(F35)) | I35: =IF(H35="","",LEN(H35)) | K35: =IF(J35="","",LEN(J35))
A36: =IF(B36="","",ROW()-1) | C36: =IF(B36="","",LEN(TRIM(B36))) | G36: =IF(F36="","",LEN(F36)) | I36: =IF(H36="","",LEN(H36)) | K36: =IF(J36="","",LEN(J36))
A37: =IF(B37="","",ROW()-1) | C37: =IF(B37="","",LEN(TRIM(B37))) | G37: =IF(F37="","",LEN(F37)) | I37: =IF(H37="","",LEN(H37)) | K37: =IF(J37="","",LEN(J37))
A38: =IF(B38="","",ROW()-1) | C38: =IF(B38="","",LEN(TRIM(B38))) | G38: =IF(F38="","",LEN(F38)) | I38: =IF(H38="","",LEN(H38)) | K38: =IF(J38="","",LEN(J38))
A39: =IF(B39="","",ROW()-1) | C39: =IF(B39="","",LEN(TRIM(B39))) | G39: =IF(F39="","",LEN(F39)) | I39: =IF(H39="","",LEN(H39)) | K39: =IF(J39="","",LEN(J39))
A40: =IF(B40="","",ROW()-1) | C40: =IF(B40="","",LEN(TRIM(B40))) | G40: =IF(F40="","",LEN(F40)) | I40: =IF(H40="","",LEN(H40)) | K40: =IF(J40="","",LEN(J40))
A41: =IF(B41="","",ROW()-1) | C41: =IF(B41="","",LEN(TRIM(B41))) | G41: =IF(F41="","",LEN(F41)) | I41: =IF(H41="","",LEN(H41)) | K41: =IF(J41="","",LEN(J41))
... A529: =IF(B529="","",ROW()-1) | C529: =IF(B529="","",LEN(TRIM(B529))) | G529: =IF(F529="","",LEN(F529)) | I529: =IF(H529="","",LEN(H529)) | K529: =IF(J529="","",LEN(J529))

Sheet 3 letters
A1: ID | B1: Word | C1: Letters | D1: Difficulty | E1: Definition | F1: Clue 1 | G1: Len | H1: Clue 2 | I1: Len | J1: Clue 3 | K1: Len | L1: Notes
A2: =IF(B2="","",ROW()-1) -> 1 | B2: act | C2: =IF(B2="","",LEN(TRIM(B2))) -> 3 | D2: Easy | E2: perform an action, or work out or perform (an action) | F2: Do something | G2: =IF(F2="","",LEN(F2)) -> 12 | H2: Part of a play | I2: =IF(H2="","",LEN(H2)) -> 14 | K2: =IF(J2="","",LEN(J2))
A3: =IF(B3="","",ROW()-1) -> 2 | B3: add | C3: =IF(B3="","",LEN(TRIM(B3))) -> 3 | D3: Easy | E3: make an addition (to) | F3: Sum up | G3: =IF(F3="","",LEN(F3)) -> 6 | H3: Put in more | I3: =IF(H3="","",LEN(H3)) -> 11 | K3: =IF(J3="","",LEN(J3))
A4: =IF(B4="","",ROW()-1) -> 3 | B4: age | C4: =IF(B4="","",LEN(TRIM(B4))) -> 3 | D4: Easy | E4: how long something has existed | F4: Years lived | G4: =IF(F4="","",LEN(F4)) -> 11 | H4: How old you are | I4: =IF(H4="","",LEN(H4)) -> 15 | K4: =IF(J4="","",LEN(J4))
A5: =IF(B5="","",ROW()-1) -> 4 | B5: ago | C5: =IF(B5="","",LEN(TRIM(B5))) -> 3 | D5: Easy | E5: in the past | F5: In the past | G5: =IF(F5="","",LEN(F5)) -> 11 | H5: Long ___ | I5: =IF(H5="","",LEN(H5)) -> 8 | K5: =IF(J5="","",LEN(J5))
A6: =IF(B6="","",ROW()-1) -> 5 | B6: aid | C6: =IF(B6="","",LEN(TRIM(B6))) -> 3 | D6: Easy | E6: a resource | G6: =IF(F6="","",LEN(F6)) | I6: =IF(H6="","",LEN(H6)) | K6: =IF(J6="","",LEN(J6))
A7: =IF(B7="","",ROW()-1) -> 6 | B7: aim | C7: =IF(B7="","",LEN(TRIM(B7))) -> 3 | D7: Easy | E7: point or cause to go (blows, weapons, or objects such as photographic equipment) towards | F7: Goal | G7: =IF(F7="","",LEN(F7)) -> 4 | H7: Point at a target | I7: =IF(H7="","",LEN(H7)) -> 17 | K7: =IF(J7="","",LEN(J7))
A8: =IF(B8="","",ROW()-1) -> 7 | B8: air | C8: =IF(B8="","",LEN(TRIM(B8))) -> 3 | D8: Easy | E8: a mixture of gases (especially oxygen) required for breathing | F8: What we breathe | G8: =IF(F8="","",LEN(F8)) -> 15 | H8: Breeze | I8: =IF(H8="","",LEN(H8)) -> 6 | K8: =IF(J8="","",LEN(J8))
A9: =IF(B9="","",ROW()-1) -> 8 | B9: all | C9: =IF(B9="","",LEN(TRIM(B9))) -> 3 | D9: Easy | E9: quantifier | F9: Every one | G9: =IF(F9="","",LEN(F9)) -> 9 | H9: The whole lot | I9: =IF(H9="","",LEN(H9)) -> 13 | K9: =IF(J9="","",LEN(J9))
A10: =IF(B10="","",ROW()-1) -> 9 | B10: any | C10: =IF(B10="","",LEN(TRIM(B10))) -> 3 | D10: Easy | E10: one or some or every or all without specification | F10: Whichever | G10: =IF(F10="","",LEN(F10)) -> 9 | H10: Not ___ more | I10: =IF(H10="","",LEN(H10)) -> 12 | K10: =IF(J10="","",LEN(J10))
A11: =IF(B11="","",ROW()-1) -> 10 | B11: arm | C11: =IF(B11="","",LEN(TRIM(B11))) -> 3 | D11: Easy | E11: a human limb | F11: Limb with a hand | G11: =IF(F11="","",LEN(F11)) -> 16 | H11: Sleeve filler | I11: =IF(H11="","",LEN(H11)) -> 13 | K11: =IF(J11="","",LEN(J11))
A12: =IF(B12="","",ROW()-1) -> 11 | B12: art | C12: =IF(B12="","",LEN(TRIM(B12))) -> 3 | D12: Easy | E12: the products of human creativity | F12: Painting, e.g. | G12: =IF(F12="","",LEN(F12)) -> 14 | H12: Museum display | I12: =IF(H12="","",LEN(H12)) -> 14 | K12: =IF(J12="","",LEN(J12))
A13: =IF(B13="","",ROW()-1) -> 12 | B13: ask | C13: =IF(B13="","",LEN(TRIM(B13))) -> 3 | D13: Easy | E13: inquire about | F13: Pose a question | G13: =IF(F13="","",LEN(F13)) -> 15 | H13: Request | I13: =IF(H13="","",LEN(H13)) -> 7 | K13: =IF(J13="","",LEN(J13))
A14: =IF(B14="","",ROW()-1) -> 13 | B14: bad | C14: =IF(B14="","",LEN(TRIM(B14))) -> 3 | D14: Easy | E14: having undesirable or negative qualities | F14: Not good | G14: =IF(F14="","",LEN(F14)) -> 8 | H14: Naughty | I14: =IF(H14="","",LEN(H14)) -> 7 | K14: =IF(J14="","",LEN(J14))
A15: =IF(B15="","",ROW()-1) -> 14 | B15: ban | C15: =IF(B15="","",LEN(TRIM(B15))) -> 3 | D15: Easy | E15: forbid the public distribution of ( a movie or a newspaper) | G15: =IF(F15="","",LEN(F15)) | I15: =IF(H15="","",LEN(H15)) | K15: =IF(J15="","",LEN(J15))
A16: =IF(B16="","",ROW()-1) -> 15 | B16: bar | C16: =IF(B16="","",LEN(TRIM(B16))) -> 3 | D16: Easy | E16: a room or establishment where alcoholic drinks are served over a counter | F16: Candy ___ | G16: =IF(F16="","",LEN(F16)) -> 9 | H16: Rod | I16: =IF(H16="","",LEN(H16)) -> 3 | K16: =IF(J16="","",LEN(J16))
A17: =IF(B17="","",ROW()-1) -> 16 | B17: bed | C17: =IF(B17="","",LEN(TRIM(B17))) -> 3 | D17: Easy | E17: a piece of furniture that provides a place to sleep | F17: Place to sleep | G17: =IF(F17="","",LEN(F17)) -> 14 | H17: Garden plot | I17: =IF(H17="","",LEN(H17)) -> 11 | K17: =IF(J17="","",LEN(J17))
A18: =IF(B18="","",ROW()-1) -> 17 | B18: bet | C18: =IF(B18="","",LEN(TRIM(B18))) -> 3 | D18: Easy | E18: the money risked on a gamble | F18: Wager | G18: =IF(F18="","",LEN(F18)) -> 5 | H18: Gamble | I18: =IF(H18="","",LEN(H18)) -> 6 | K18: =IF(J18="","",LEN(J18))
A19: =IF(B19="","",ROW()-1) -> 18 | B19: bid | C19: =IF(B19="","",LEN(TRIM(B19))) -> 3 | D19: Easy | E19: propose a payment | F19: Offer at auction | G19: =IF(F19="","",LEN(F19)) -> 16 | H19: Attempt | I19: =IF(H19="","",LEN(H19)) -> 7 | K19: =IF(J19="","",LEN(J19))
A20: =IF(B20="","",ROW()-1) -> 19 | B20: big | C20: =IF(B20="","",LEN(TRIM(B20))) -> 3 | D20: Easy | E20: above average in size or number or quantity or magnitude or extent | F20: Large | G20: =IF(F20="","",LEN(F20)) -> 5 | H20: Huge | I20: =IF(H20="","",LEN(H20)) -> 4 | K20: =IF(J20="","",LEN(J20))
A21: =IF(B21="","",ROW()-1) -> 20 | B21: bit | C21: =IF(B21="","",LEN(TRIM(B21))) -> 3 | D21: Easy | E21: a small piece or quantity of something | G21: =IF(F21="","",LEN(F21)) | I21: =IF(H21="","",LEN(H21)) | K21: =IF(J21="","",LEN(J21))
A22: =IF(B22="","",ROW()-1) -> 21 | B22: box | C22: =IF(B22="","",LEN(TRIM(B22))) -> 3 | D22: Easy | E22: a (usually rectangular) container | G22: =IF(F22="","",LEN(F22)) | I22: =IF(H22="","",LEN(H22)) | K22: =IF(J22="","",LEN(J22))
A23: =IF(B23="","",ROW()-1) -> 22 | B23: boy | C23: =IF(B23="","",LEN(TRIM(B23))) -> 3 | D23: Easy | E23: a youthful male person | G23: =IF(F23="","",LEN(F23)) | I23: =IF(H23="","",LEN(H23)) | K23: =IF(J23="","",LEN(J23))
A24: =IF(B24="","",ROW()-1) -> 23 | B24: bug | C24: =IF(B24="","",LEN(TRIM(B24))) -> 3 | D24: Easy | E24: general term for any insect or similar creeping or crawling invertebrate | F24: Insect | G24: =IF(F24="","",LEN(F24)) -> 6 | H24: Glitch | I24: =IF(H24="","",LEN(H24)) -> 6 | K24: =IF(J24="","",LEN(J24))
A25: =IF(B25="","",ROW()-1) -> 24 | B25: bus | C25: =IF(B25="","",LEN(TRIM(B25))) -> 3 | D25: Easy | E25: a vehicle carrying many passengers | F25: School ___ | G25: =IF(F25="","",LEN(F25)) -> 10 | H25: Public transport | I25: =IF(H25="","",LEN(H25)) -> 16 | K25: =IF(J25="","",LEN(J25))
A26: =IF(B26="","",ROW()-1) -> 25 | B26: but | C26: =IF(B26="","",LEN(TRIM(B26))) -> 3 | D26: Easy | E26: and nothing more | F26: However | G26: =IF(F26="","",LEN(F26)) -> 7 | H26: Yet | I26: =IF(H26="","",LEN(H26)) -> 3 | K26: =IF(J26="","",LEN(J26))
A27: =IF(B27="","",ROW()-1) -> 26 | B27: buy | C27: =IF(B27="","",LEN(TRIM(B27))) -> 3 | D27: Easy | E27: obtain by purchase | G27: =IF(F27="","",LEN(F27)) | I27: =IF(H27="","",LEN(H27)) | K27: =IF(J27="","",LEN(J27))
A28: =IF(B28="","",ROW()-1) -> 27 | B28: can | C28: =IF(B28="","",LEN(TRIM(B28))) -> 3 | D28: Easy | E28: preserve in a can or tin | G28: =IF(F28="","",LEN(F28)) | I28: =IF(H28="","",LEN(H28)) | K28: =IF(J28="","",LEN(J28))
A29: =IF(B29="","",ROW()-1) -> 28 | B29: car | C29: =IF(B29="","",LEN(TRIM(B29))) -> 3 | D29: Easy | E29: a motor vehicle with four wheels | F29: Auto | G29: =IF(F29="","",LEN(F29)) -> 4 | H29: Sedan | I29: =IF(H29="","",LEN(H29)) -> 5 | K29: =IF(J29="","",LEN(J29))
A30: =IF(B30="","",ROW()-1) -> 29 | B30: cat | C30: =IF(B30="","",LEN(TRIM(B30))) -> 3 | D30: Easy | E30: feline mammal usually having thick soft fur and no ability to roar: domestic cats | F30: Purring pet | G30: =IF(F30="","",LEN(F30)) -> 11 | H30: Kitty | I30: =IF(H30="","",LEN(H30)) -> 5 | K30: =IF(J30="","",LEN(J30))
A31: =IF(B31="","",ROW()-1) -> 30 | B31: cry | C31: =IF(B31="","",LEN(TRIM(B31))) -> 3 | D31: Easy | E31: a loud utterance | G31: =IF(F31="","",LEN(F31)) | I31: =IF(H31="","",LEN(H31)) | K31: =IF(J31="","",LEN(J31))
A32: =IF(B32="","",ROW()-1) -> 31 | B32: cup | C32: =IF(B32="","",LEN(TRIM(B32))) -> 3 | D32: Easy | E32: a small open container usually used for drinking | F32: Mug | G32: =IF(F32="","",LEN(F32)) -> 3 | H32: Trophy | I32: =IF(H32="","",LEN(H32)) -> 6 | K32: =IF(J32="","",LEN(J32))
A33: =IF(B33="","",ROW()-1) -> 32 | B33: cut | C33: =IF(B33="","",LEN(TRIM(B33))) -> 3 | D33: Easy | E33: separate with or as if with an instrument | F33: Slice | G33: =IF(F33="","",LEN(F33)) -> 5 | H33: Snip | I33: =IF(H33="","",LEN(H33)) -> 4 | K33: =IF(J33="","",LEN(J33))
A34: =IF(B34="","",ROW()-1) -> 33 | B34: day | C34: =IF(B34="","",LEN(TRIM(B34))) -> 3 | D34: Easy | E34: time for Earth to make a complete rotation on its axis | F34: 24 hours | G34: =IF(F34="","",LEN(F34)) -> 8 | H34: Not night | I34: =IF(H34="","",LEN(H34)) -> 9 | K34: =IF(J34="","",LEN(J34))
A35: =IF(B35="","",ROW()-1) -> 34 | B35: doe | C35: =IF(B35="","",LEN(TRIM(B35))) -> 3 | D35: Easy | E35: the federal department responsible for maintaining a national energy policy of the United States | F35: Female deer | G35: =IF(F35="","",LEN(F35)) -> 11 | H35: Mother deer | I35: =IF(H35="","",LEN(H35)) -> 11 | K35: =IF(J35="","",LEN(J35))
A36: =IF(B36="","",ROW()-1) -> 35 | B36: dog | C36: =IF(B36="","",LEN(TRIM(B36))) -> 3 | D36: Easy | E36: a member of the genus Canis (probably descended from the common wolf) that has been domesticated by man since prehistoric times | G36: =IF(F36="","",LEN(F36)) | I36: =IF(H36="","",LEN(H36)) | K36: =IF(J36="","",LEN(J36))
A37: =IF(B37="","",ROW()-1) -> 36 | B37: dry | C37: =IF(B37="","",LEN(TRIM(B37))) -> 3 | D37: Easy | E37: remove the moisture from and make dry | F37: Not wet | G37: =IF(F37="","",LEN(F37)) -> 7 | H37: Arid | I37: =IF(H37="","",LEN(H37)) -> 4 | K37: =IF(J37="","",LEN(J37))
A38: =IF(B38="","",ROW()-1) -> 37 | B38: due | C38: =IF(B38="","",LEN(TRIM(B38))) -> 3 | D38: Easy | E38: owed and payable immediately or on demand | F38: Owed | G38: =IF(F38="","",LEN(F38)) -> 4 | H38: Expected | I38: =IF(H38="","",LEN(H38)) -> 8 | K38: =IF(J38="","",LEN(J38))
A39: =IF(B39="","",ROW()-1) -> 38 | B39: eat | C39: =IF(B39="","",LEN(TRIM(B39))) -> 3 | D39: Easy | E39: take in solid food | F39: Dine | G39: =IF(F39="","",LEN(F39)) -> 4 | H39: Have a meal | I39: =IF(H39="","",LEN(H39)) -> 11 | K39: =IF(J39="","",LEN(J39))
A40: =IF(B40="","",ROW()-1) -> 39 | B40: end | C40: =IF(B40="","",LEN(TRIM(B40))) -> 3 | D40: Easy | E40: either extremity of something that has length | F40: Finish | G40: =IF(F40="","",LEN(F40)) -> 6 | H40: Conclusion | I40: =IF(H40="","",LEN(H40)) -> 10 | K40: =IF(J40="","",LEN(J40))
A41: =IF(B41="","",ROW()-1) -> 40 | B41: err | C41: =IF(B41="","",LEN(TRIM(B41))) -> 3 | D41: Easy | E41: to make a mistake or be incorrect | F41: Make a mistake | G41: =IF(F41="","",LEN(F41)) -> 14 | H41: Slip up | I41: =IF(H41="","",LEN(H41)) -> 7 | K41: =IF(J41="","",LEN(J41))
A42: =IF(B42="","",ROW()-1) -> 41 | B42: eye | C42: =IF(B42="","",LEN(TRIM(B42))) -> 3 | D42: Easy | E42: the organ of sight | F42: Seeing organ | G42: =IF(F42="","",LEN(F42)) -> 12 | H42: Look at | I42: =IF(H42="","",LEN(H42)) -> 7 | K42: =IF(J42="","",LEN(J42))
A43: =IF(B43="","",ROW()-1) -> 42 | B43: fan | C43: =IF(B43="","",LEN(TRIM(B43))) -> 3 | D43: Easy | E43: a device for creating a current of air by movement of a surface or surfaces | F43: Supporter | G43: =IF(F43="","",LEN(F43)) -> 9 | H43: Cooling device | I43: =IF(H43="","",LEN(H43)) -> 14 | K43: =IF(J43="","",LEN(J43))
A44: =IF(B44="","",ROW()-1) -> 43 | B44: far | C44: =IF(B44="","",LEN(TRIM(B44))) -> 3 | D44: Easy | E44: to a considerable degree | F44: Distant | G44: =IF(F44="","",LEN(F44)) -> 7 | H44: Not near | I44: =IF(H44="","",LEN(H44)) -> 8 | K44: =IF(J44="","",LEN(J44))
A45: =IF(B45="","",ROW()-1) -> 44 | B45: fed | C45: =IF(B45="","",LEN(TRIM(B45))) -> 3 | D45: Easy | E45: any federal law-enforcement officer | G45: =IF(F45="","",LEN(F45)) | I45: =IF(H45="","",LEN(H45)) | K45: =IF(J45="","",LEN(J45))
A46: =IF(B46="","",ROW()-1) -> 45 | B46: few | C46: =IF(B46="","",LEN(TRIM(B46))) -> 3 | D46: Easy | E46: a quantifier that can be used with count nouns and is often preceded by `a' | G46: =IF(F46="","",LEN(F46)) | I46: =IF(H46="","",LEN(H46)) | K46: =IF(J46="","",LEN(J46))
A47: =IF(B47="","",ROW()-1) -> 46 | B47: fit | C47: =IF(B47="","",LEN(TRIM(B47))) -> 3 | D47: Easy | E47: be agreeable or acceptable to | G47: =IF(F47="","",LEN(F47)) | I47: =IF(H47="","",LEN(H47)) | K47: =IF(J47="","",LEN(J47))
A48: =IF(B48="","",ROW()-1) -> 47 | B48: fix | C48: =IF(B48="","",LEN(TRIM(B48))) -> 3 | D48: Easy | E48: restore by replacing a part or putting together what is torn or broken | G48: =IF(F48="","",LEN(F48)) | I48: =IF(H48="","",LEN(H48)) | K48: =IF(J48="","",LEN(J48))
A49: =IF(B49="","",ROW()-1) -> 48 | B49: fly | C49: =IF(B49="","",LEN(TRIM(B49))) -> 3 | D49: Easy | E49: travel through the air | F49: Soar | G49: =IF(F49="","",LEN(F49)) -> 4 | H49: Buzzing insect | I49: =IF(H49="","",LEN(H49)) -> 14 | K49: =IF(J49="","",LEN(J49))
A50: =IF(B50="","",ROW()-1) -> 49 | B50: fry | C50: =IF(B50="","",LEN(TRIM(B50))) -> 3 | D50: Easy | E50: be excessively hot | G50: =IF(F50="","",LEN(F50)) | I50: =IF(H50="","",LEN(H50)) | K50: =IF(J50="","",LEN(J50))
A51: =IF(B51="","",ROW()-1) -> 50 | B51: fun | C51: =IF(B51="","",LEN(TRIM(B51))) -> 3 | D51: Easy | E51: activities that are enjoyable or amusing | F51: Enjoyment | G51: =IF(F51="","",LEN(F51)) -> 9 | H51: Good time | I51: =IF(H51="","",LEN(H51)) -> 9 | K51: =IF(J51="","",LEN(J51))
A52: =IF(B52="","",ROW()-1) -> 51 | B52: gap | C52: =IF(B52="","",LEN(TRIM(B52))) -> 3 | D52: Easy | E52: a conspicuous disparity or difference as between two figures | F52: Opening | G52: =IF(F52="","",LEN(F52)) -> 7 | H52: Space between | I52: =IF(H52="","",LEN(H52)) -> 13 | K52: =IF(J52="","",LEN(J52))
A53: =IF(B53="","",ROW()-1) -> 52 | B53: gas | C53: =IF(B53="","",LEN(TRIM(B53))) -> 3 | D53: Easy | E53: the state of matter distinguished from the solid and liquid states by: relatively low density and viscosity | F53: Fuel | G53: =IF(F53="","",LEN(F53)) -> 4 | H53: Air-like substance | I53: =IF(H53="","",LEN(H53)) -> 18 | K53: =IF(J53="","",LEN(J53))
A54: =IF(B54="","",ROW()-1) -> 53 | B54: get | C54: =IF(B54="","",LEN(TRIM(B54))) -> 3 | D54: Easy | E54: come into the possession of something concrete or abstract | F54: Receive | G54: =IF(F54="","",LEN(F54)) -> 7 | H54: Obtain | I54: =IF(H54="","",LEN(H54)) -> 6 | K54: =IF(J54="","",LEN(J54))
A55: =IF(B55="","",ROW()-1) -> 54 | B55: guy | C55: =IF(B55="","",LEN(TRIM(B55))) -> 3 | D55: Easy | E55: an informal term for a youth or man | G55: =IF(F55="","",LEN(F55)) | I55: =IF(H55="","",LEN(H55)) | K55: =IF(J55="","",LEN(J55))
A56: =IF(B56="","",ROW()-1) -> 55 | B56: hat | C56: =IF(B56="","",LEN(TRIM(B56))) -> 3 | D56: Easy | E56: headdress that protects the head from bad weather | F56: Cap | G56: =IF(F56="","",LEN(F56)) -> 3 | H56: Head cover | I56: =IF(H56="","",LEN(H56)) -> 10 | K56: =IF(J56="","",LEN(J56))
A57: =IF(B57="","",ROW()-1) -> 56 | B57: hit | C57: =IF(B57="","",LEN(TRIM(B57))) -> 3 | D57: Easy | E57: cause to move by striking | F57: Strike | G57: =IF(F57="","",LEN(F57)) -> 6 | H57: Big success | I57: =IF(H57="","",LEN(H57)) -> 11 | K57: =IF(J57="","",LEN(J57))
A58: =IF(B58="","",ROW()-1) -> 57 | B58: hot | C58: =IF(B58="","",LEN(TRIM(B58))) -> 3 | D58: Easy | E58: used of physical heat | F58: Very warm | G58: =IF(F58="","",LEN(F58)) -> 9 | H58: Spicy | I58: =IF(H58="","",LEN(H58)) -> 5 | K58: =IF(J58="","",LEN(J58))
A59: =IF(B59="","",ROW()-1) -> 58 | B59: ice | C59: =IF(B59="","",LEN(TRIM(B59))) -> 3 | D59: Easy | E59: water frozen in the solid state | F59: Frozen water | G59: =IF(F59="","",LEN(F59)) -> 12 | H59: Rink surface | I59: =IF(H59="","",LEN(H59)) -> 12 | K59: =IF(J59="","",LEN(J59))
A60: =IF(B60="","",ROW()-1) -> 59 | B60: ill | C60: =IF(B60="","",LEN(TRIM(B60))) -> 3 | D60: Easy | E60: affected by an impairment of normal physical or mental function | F60: Sick | G60: =IF(F60="","",LEN(F60)) -> 4 | H60: Unwell | I60: =IF(H60="","",LEN(H60)) -> 6 | K60: =IF(J60="","",LEN(J60))
A61: =IF(B61="","",ROW()-1) -> 60 | B61: job | C61: =IF(B61="","",LEN(TRIM(B61))) -> 3 | D61: Easy | E61: the principal activity in your life that you do to earn money | G61: =IF(F61="","",LEN(F61)) | I61: =IF(H61="","",LEN(H61)) | K61: =IF(J61="","",LEN(J61))
A62: =IF(B62="","",ROW()-1) -> 61 | B62: joy | C62: =IF(B62="","",LEN(TRIM(B62))) -> 3 | D62: Easy | E62: the emotion of great happiness | G62: =IF(F62="","",LEN(F62)) | I62: =IF(H62="","",LEN(H62)) | K62: =IF(J62="","",LEN(J62))
A63: =IF(B63="","",ROW()-1) -> 62 | B63: key | C63: =IF(B63="","",LEN(TRIM(B63))) -> 3 | D63: Easy | E63: metal device shaped in such a way that when it is inserted into the appropriate lock the lock's mechanism can be rotated | G63: =IF(F63="","",LEN(F63)) | I63: =IF(H63="","",LEN(H63)) | K63: =IF(J63="","",LEN(J63))
A64: =IF(B64="","",ROW()-1) -> 63 | B64: kid | C64: =IF(B64="","",LEN(TRIM(B64))) -> 3 | D64: Easy | E64: tell false information to for fun | G64: =IF(F64="","",LEN(F64)) | I64: =IF(H64="","",LEN(H64)) | K64: =IF(J64="","",LEN(J64))
A65: =IF(B65="","",ROW()-1) -> 64 | B65: law | C65: =IF(B65="","",LEN(TRIM(B65))) -> 3 | D65: Easy | E65: the collection of rules imposed by authority | F65: Rule | G65: =IF(F65="","",LEN(F65)) -> 4 | H65: Legal code | I65: =IF(H65="","",LEN(H65)) -> 10 | K65: =IF(J65="","",LEN(J65))
A66: =IF(B66="","",ROW()-1) -> 65 | B66: lay | C66: =IF(B66="","",LEN(TRIM(B66))) -> 3 | D66: Easy | E66: put into a certain place or abstract location | G66: =IF(F66="","",LEN(F66)) | I66: =IF(H66="","",LEN(H66)) | K66: =IF(J66="","",LEN(J66))
A67: =IF(B67="","",ROW()-1) -> 66 | B67: leg | C67: =IF(B67="","",LEN(TRIM(B67))) -> 3 | D67: Easy | E67: a human limb | F67: Limb | G67: =IF(F67="","",LEN(F67)) -> 4 | H67: Table support | I67: =IF(H67="","",LEN(H67)) -> 13 | K67: =IF(J67="","",LEN(J67))
A68: =IF(B68="","",ROW()-1) -> 67 | B68: let | C68: =IF(B68="","",LEN(TRIM(B68))) -> 3 | D68: Easy | E68: make it possible through a specific action or lack of action for something to happen | F68: Allow | G68: =IF(F68="","",LEN(F68)) -> 5 | H68: Permit | I68: =IF(H68="","",LEN(H68)) -> 6 | K68: =IF(J68="","",LEN(J68))
A69: =IF(B69="","",ROW()-1) -> 68 | B69: lie | C69: =IF(B69="","",LEN(TRIM(B69))) -> 3 | D69: Easy | E69: be located or situated somewhere | F69: Fib | G69: =IF(F69="","",LEN(F69)) -> 3 | H69: Recline | I69: =IF(H69="","",LEN(H69)) -> 7 | K69: =IF(J69="","",LEN(J69))
A70: =IF(B70="","",ROW()-1) -> 69 | B70: log | C70: =IF(B70="","",LEN(TRIM(B70))) -> 3 | D70: Easy | E70: enter into a log, as on ships and planes | G70: =IF(F70="","",LEN(F70)) | I70: =IF(H70="","",LEN(H70)) | K70: =IF(J70="","",LEN(J70))
A71: =IF(B71="","",ROW()-1) -> 70 | B71: lot | C71: =IF(B71="","",LEN(TRIM(B71))) -> 3 | D71: Easy | E71: (often followed by `of') a large number or amount or extent | F71: Many | G71: =IF(F71="","",LEN(F71)) -> 4 | H71: Parking area | I71: =IF(H71="","",LEN(H71)) -> 12 | K71: =IF(J71="","",LEN(J71))
A72: =IF(B72="","",ROW()-1) -> 71 | B72: low | C72: =IF(B72="","",LEN(TRIM(B72))) -> 3 | D72: Easy | E72: less than normal in degree or intensity or amount | G72: =IF(F72="","",LEN(F72)) | I72: =IF(H72="","",LEN(H72)) | K72: =IF(J72="","",LEN(J72))
A73: =IF(B73="","",ROW()-1) -> 72 | B73: mad | C73: =IF(B73="","",LEN(TRIM(B73))) -> 3 | D73: Easy | E73: roused to anger | F73: Angry | G73: =IF(F73="","",LEN(F73)) -> 5 | H73: Crazy | I73: =IF(H73="","",LEN(H73)) -> 5 | K73: =IF(J73="","",LEN(J73))
A74: =IF(B74="","",ROW()-1) -> 73 | B74: man | C74: =IF(B74="","",LEN(TRIM(B74))) -> 3 | D74: Easy | E74: an adult person who is male (as opposed to a woman) | G74: =IF(F74="","",LEN(F74)) | I74: =IF(H74="","",LEN(H74)) | K74: =IF(J74="","",LEN(J74))
A75: =IF(B75="","",ROW()-1) -> 74 | B75: map | C75: =IF(B75="","",LEN(TRIM(B75))) -> 3 | D75: Easy | E75: make a map of | F75: Atlas page | G75: =IF(F75="","",LEN(F75)) -> 10 | H75: Chart | I75: =IF(H75="","",LEN(H75)) -> 5 | K75: =IF(J75="","",LEN(J75))
A76: =IF(B76="","",ROW()-1) -> 75 | B76: may | C76: =IF(B76="","",LEN(TRIM(B76))) -> 3 | D76: Easy | E76: the month following April and preceding June | G76: =IF(F76="","",LEN(F76)) | I76: =IF(H76="","",LEN(H76)) | K76: =IF(J76="","",LEN(J76))
A77: =IF(B77="","",ROW()-1) -> 76 | B77: mix | C77: =IF(B77="","",LEN(TRIM(B77))) -> 3 | D77: Easy | E77: mix together different elements | G77: =IF(F77="","",LEN(F77)) | I77: =IF(H77="","",LEN(H77)) | K77: =IF(J77="","",LEN(J77))
A78: =IF(B78="","",ROW()-1) -> 77 | B78: net | C78: =IF(B78="","",LEN(TRIM(B78))) -> 3 | D78: Easy | E78: a computer network consisting of a worldwide network of computer networks that use the TCP/IP network protocols to facilitate data transmission and exchange | F78: Fishing mesh | G78: =IF(F78="","",LEN(F78)) -> 12 | H78: Goal mesh | I78: =IF(H78="","",LEN(H78)) -> 9 | K78: =IF(J78="","",LEN(J78))
A79: =IF(B79="","",ROW()-1) -> 78 | B79: new | C79: =IF(B79="","",LEN(TRIM(B79))) -> 3 | D79: Easy | E79: not of long duration | G79: =IF(F79="","",LEN(F79)) | I79: =IF(H79="","",LEN(H79)) | K79: =IF(J79="","",LEN(J79))
A80: =IF(B80="","",ROW()-1) -> 79 | B80: not | C80: =IF(B80="","",LEN(TRIM(B80))) -> 3 | D80: Easy | E80: negation of a word or group of words | F80: Negative word | G80: =IF(F80="","",LEN(F80)) -> 13 | H80: ___ at all | I80: =IF(H80="","",LEN(H80)) -> 10 | K80: =IF(J80="","",LEN(J80))
A81: =IF(B81="","",ROW()-1) -> 80 | B81: now | C81: =IF(B81="","",LEN(TRIM(B81))) -> 3 | D81: Easy | E81: in the historical present | F81: At once | G81: =IF(F81="","",LEN(F81)) -> 7 | H81: Right away | I81: =IF(H81="","",LEN(H81)) -> 10 | K81: =IF(J81="","",LEN(J81))
A82: =IF(B82="","",ROW()-1) -> 81 | B82: odd | C82: =IF(B82="","",LEN(TRIM(B82))) -> 3 | D82: Easy | E82: not divisible by two | F82: Strange | G82: =IF(F82="","",LEN(F82)) -> 7 | H82: 1, 3 or 5 | I82: =IF(H82="","",LEN(H82)) -> 9 | K82: =IF(J82="","",LEN(J82))
A83: =IF(B83="","",ROW()-1) -> 82 | B83: off | C83: =IF(B83="","",LEN(TRIM(B83))) -> 3 | D83: Easy | E83: from a particular thing or place or position (`forth' is obsolete) | F83: Not on | G83: =IF(F83="","",LEN(F83)) -> 6 | H83: Away | I83: =IF(H83="","",LEN(H83)) -> 4 | K83: =IF(J83="","",LEN(J83))
A84: =IF(B84="","",ROW()-1) -> 83 | B84: oil | C84: =IF(B84="","",LEN(TRIM(B84))) -> 3 | D84: Easy | E84: a slippery or viscous liquid or liquefiable substance not miscible with water | F84: Cooking fat | G84: =IF(F84="","",LEN(F84)) -> 11 | H84: Fuel | I84: =IF(H84="","",LEN(H84)) -> 4 | K84: =IF(J84="","",LEN(J84))
A85: =IF(B85="","",ROW()-1) -> 84 | B85: old | C85: =IF(B85="","",LEN(TRIM(B85))) -> 3 | D85: Easy | E85: (used especially of persons) having lived for a relatively long time or attained a specific age | F85: Aged | G85: =IF(F85="","",LEN(F85)) -> 4 | H85: Not new | I85: =IF(H85="","",LEN(H85)) -> 7 | K85: =IF(J85="","",LEN(J85))
A86: =IF(B86="","",ROW()-1) -> 85 | B86: one | C86: =IF(B86="","",LEN(TRIM(B86))) -> 3 | D86: Easy | E86: used of a single unit or thing | F86: Single | G86: =IF(F86="","",LEN(F86)) -> 6 | H86: First number | I86: =IF(H86="","",LEN(H86)) -> 12 | K86: =IF(J86="","",LEN(J86))
A87: =IF(B87="","",ROW()-1) -> 86 | B87: out | C87: =IF(B87="","",LEN(TRIM(B87))) -> 3 | D87: Easy | E87: not allowed to continue to bat or run | F87: Not in | G87: =IF(F87="","",LEN(F87)) -> 6 | H87: Away | I87: =IF(H87="","",LEN(H87)) -> 4 | K87: =IF(J87="","",LEN(J87))
A88: =IF(B88="","",ROW()-1) -> 87 | B88: owe | C88: =IF(B88="","",LEN(TRIM(B88))) -> 3 | D88: Easy | E88: be obliged to pay or repay | F88: Be in debt | G88: =IF(F88="","",LEN(F88)) -> 10 | H88: Must pay | I88: =IF(H88="","",LEN(H88)) -> 8 | K88: =IF(J88="","",LEN(J88))
A89: =IF(B89="","",ROW()-1) -> 88 | B89: own | C89: =IF(B89="","",LEN(TRIM(B89))) -> 3 | D89: Easy | E89: have ownership or possession of | F89: Possess | G89: =IF(F89="","",LEN(F89)) -> 7 | H89: Have | I89: =IF(H89="","",LEN(H89)) -> 4 | K89: =IF(J89="","",LEN(J89))
A90: =IF(B90="","",ROW()-1) -> 89 | B90: pay | C90: =IF(B90="","",LEN(TRIM(B90))) -> 3 | D90: Easy | E90: give money, usually in exchange for goods or services | F90: Wages | G90: =IF(F90="","",LEN(F90)) -> 5 | H90: Settle a bill | I90: =IF(H90="","",LEN(H90)) -> 13 | K90: =IF(J90="","",LEN(J90))
A91: =IF(B91="","",ROW()-1) -> 90 | B91: pen | C91: =IF(B91="","",LEN(TRIM(B91))) -> 3 | D91: Easy | E91: a writing implement with a point from which ink flows | F91: Writing tool | G91: =IF(F91="","",LEN(F91)) -> 12 | H91: Pig enclosure | I91: =IF(H91="","",LEN(H91)) -> 13 | K91: =IF(J91="","",LEN(J91))
... A98: =IF(B98="","",ROW()-1) -> 97 | B98: run | C98: =IF(B98="","",LEN(TRIM(B98))) -> 3 | D98: Easy | E98: move fast by using one's feet, with one foot off the ground at any given time | F98: Sprint | G98: =IF(F98="","",LEN(F98)) -> 6 | H98: Jog | I98: =IF(H98="","",LEN(H98)) -> 3 | K98: =IF(J98="","",LEN(J98))
A99: =IF(B99="","",ROW()-1) -> 98 | B99: sad | C99: =IF(B99="","",LEN(TRIM(B99))) -> 3 | D99: Easy | E99: experiencing or showing sorrow or unhappiness | G99: =IF(F99="","",LEN(F99)) | I99: =IF(H99="","",LEN(H99)) | K99: =IF(J99="","",LEN(J99))
A100: =IF(B100="","",ROW()-1) -> 99 | B100: sat | C100: =IF(B100="","",LEN(TRIM(B100))) -> 3 | D100: Easy | E100: the seventh and last day of the week | F100: Was seated | G100: =IF(F100="","",LEN(F100)) -> 10 | H100: Took a seat | I100: =IF(H100="","",LEN(H100)) -> 11 | K100: =IF(J100="","",LEN(J100))
A101: =IF(B101="","",ROW()-1) -> 100 | B101: saw | C101: =IF(B101="","",LEN(TRIM(B101))) -> 3 | D101: Easy | E101: cut with a saw | G101: =IF(F101="","",LEN(F101)) | I101: =IF(H101="","",LEN(H101)) | K101: =IF(J101="","",LEN(J101))
A102: =IF(B102="","",ROW()-1) -> 101 | B102: say | C102: =IF(B102="","",LEN(TRIM(B102))) -> 3 | D102: Easy | E102: express in words | F102: Speak | G102: =IF(F102="","",LEN(F102)) -> 5 | H102: State | I102: =IF(H102="","",LEN(H102)) -> 5 | K102: =IF(J102="","",LEN(J102))
A103: =IF(B103="","",ROW()-1) -> 102 | B103: see | C103: =IF(B103="","",LEN(TRIM(B103))) -> 3 | D103: Easy | E103: perceive by sight or have the power to perceive by sight | F103: Look | G103: =IF(F103="","",LEN(F103)) -> 4 | H103: Spot | I103: =IF(H103="","",LEN(H103)) -> 4 | K103: =IF(J103="","",LEN(J103))
A104: =IF(B104="","",ROW()-1) -> 103 | B104: set | C104: =IF(B104="","",LEN(TRIM(B104))) -> 3 | D104: Easy | E104: put into a certain place or abstract location | F104: Put | G104: =IF(F104="","",LEN(F104)) -> 3 | H104: Group | I104: =IF(H104="","",LEN(H104)) -> 5 | K104: =IF(J104="","",LEN(J104))
A105: =IF(B105="","",ROW()-1) -> 104 | B105: sit | C105: =IF(B105="","",LEN(TRIM(B105))) -> 3 | D105: Easy | E105: be seated | F105: Be seated | G105: =IF(F105="","",LEN(F105)) -> 9 | H105: Take a chair | I105: =IF(H105="","",LEN(H105)) -> 12 | K105: =IF(J105="","",LEN(J105))
A106: =IF(B106="","",ROW()-1) -> 105 | B106: six | C106: =IF(B106="","",LEN(TRIM(B106))) -> 3 | D106: Easy | E106: the cardinal number that is the sum of five and one | G106: =IF(F106="","",LEN(F106)) | I106: =IF(H106="","",LEN(H106)) | K106: =IF(J106="","",LEN(J106))
...

Sheet 4 letters
A1: ID | B1: Word | C1: Letters | D1: Difficulty | E1: Definition | F1: Clue 1 | G1: Len | H1: Clue 2 | I1: Len | J1: Clue 3 | K1: Len | L1: Notes
A2: =IF(B2="","",ROW()-1) -> 1 | B2: able | C2: =IF(B2="","",LEN(TRIM(B2))) -> 4 | D2: Easy | E2: (usually followed by `to') having the necessary means or skill or know-how or authority to do something | F2: Capable | G2: =IF(F2="","",LEN(F2)) -> 7 | H2: Having the skill | I2: =IF(H2="","",LEN(H2)) -> 16 | K2: =IF(J2="","",LEN(J2))
A3: =IF(B3="","",ROW()-1) -> 2 | B3: also | C3: =IF(B3="","",LEN(TRIM(B3))) -> 4 | D3: Easy | E3: in addition | G3: =IF(F3="","",LEN(F3)) | I3: =IF(H3="","",LEN(H3)) | K3: =IF(J3="","",LEN(J3))
A4: =IF(B4="","",ROW()-1) -> 3 | B4: area | C4: =IF(B4="","",LEN(TRIM(B4))) -> 4 | D4: Easy | E4: a particular geographical region of indefinite boundary (usually serving some special purpose or distinguished by its people or culture or geography) | F4: Region | G4: =IF(F4="","",LEN(F4)) -> 6 | H4: Zone | I4: =IF(H4="","",LEN(H4)) -> 4 | K4: =IF(J4="","",LEN(J4))
A5: =IF(B5="","",ROW()-1) -> 4 | B5: army | C5: =IF(B5="","",LEN(TRIM(B5))) -> 4 | D5: Easy | E5: a permanent organization of the military land forces of a nation or state | F5: Soldiers | G5: =IF(F5="","",LEN(F5)) -> 8 | H5: Military force | I5: =IF(H5="","",LEN(H5)) -> 14 | K5: =IF(J5="","",LEN(J5))
A6: =IF(B6="","",ROW()-1) -> 5 | B6: away | C6: =IF(B6="","",LEN(TRIM(B6))) -> 4 | D6: Easy | E6: from a particular thing or place or position (`forth' is obsolete) | G6: =IF(F6="","",LEN(F6)) | I6: =IF(H6="","",LEN(H6)) | K6: =IF(J6="","",LEN(J6))
A7: =IF(B7="","",ROW()-1) -> 6 | B7: back | C7: =IF(B7="","",LEN(TRIM(B7))) -> 4 | D7: Easy | E7: in or to or toward a former location | G7: =IF(F7="","",LEN(F7)) | I7: =IF(H7="","",LEN(H7)) | K7: =IF(J7="","",LEN(J7))
A8: =IF(B8="","",ROW()-1) -> 7 | B8: ball | C8: =IF(B8="","",LEN(TRIM(B8))) -> 4 | D8: Easy | E8: round object that is hit or thrown or kicked in games | F8: Round toy | G8: =IF(F8="","",LEN(F8)) -> 9 | H8: Dance with gowns | I8: =IF(H8="","",LEN(H8)) -> 16 | K8: =IF(J8="","",LEN(J8))
A9: =IF(B9="","",ROW()-1) -> 8 | B9: band | C9: =IF(B9="","",LEN(TRIM(B9))) -> 4 | D9: Easy | E9: an unofficial association of people or groups | G9: =IF(F9="","",LEN(F9)) | I9: =IF(H9="","",LEN(H9)) | K9: =IF(J9="","",LEN(J9))
A10: =IF(B10="","",ROW()-1) -> 9 | B10: bank | C10: =IF(B10="","",LEN(TRIM(B10))) -> 4 | D10: Easy | E10: sloping land (especially the slope beside a body of water) | G10: =IF(F10="","",LEN(F10)) | I10: =IF(H10="","",LEN(H10)) | K10: =IF(J10="","",LEN(J10))
A11: =IF(B11="","",ROW()-1) -> 10 | B11: base | C11: =IF(B11="","",LEN(TRIM(B11))) -> 4 | D11: Easy | E11: installation from which a military force initiates operations | F11: Bottom | G11: =IF(F11="","",LEN(F11)) -> 6 | H11: Foundation | I11: =IF(H11="","",LEN(H11)) -> 10 | K11: =IF(J11="","",LEN(J11))
A12: =IF(B12="","",ROW()-1) -> 11 | B12: bear | C12: =IF(B12="","",LEN(TRIM(B12))) -> 4 | D12: Easy | E12: have | F12: Grizzly | G12: =IF(F12="","",LEN(F12)) -> 7 | H12: Put up with | I12: =IF(H12="","",LEN(H12)) -> 11 | K12: =IF(J12="","",LEN(J12))
A13: =IF(B13="","",ROW()-1) -> 12 | B13: best | C13: =IF(B13="","",LEN(TRIM(B13))) -> 4 | D13: Easy | E13: the supreme effort one can make | G13: =IF(F13="","",LEN(F13)) | I13: =IF(H13="","",LEN(H13)) | K13: =IF(J13="","",LEN(J13))
A14: =IF(B14="","",ROW()-1) -> 13 | B14: bill | C14: =IF(B14="","",LEN(TRIM(B14))) -> 4 | D14: Easy | E14: a statute in draft before it becomes law | G14: =IF(F14="","",LEN(F14)) | I14: =IF(H14="","",LEN(H14)) | K14: =IF(J14="","",LEN(J14))
A15: =IF(B15="","",ROW()-1) -> 14 | B15: bind | C15: =IF(B15="","",LEN(TRIM(B15))) -> 4 | D15: Easy | E15: stick to firmly | G15: =IF(F15="","",LEN(F15)) | I15: =IF(H15="","",LEN(H15)) | K15: =IF(J15="","",LEN(J15))
A16: =IF(B16="","",ROW()-1) -> 15 | B16: bite | C16: =IF(B16="","",LEN(TRIM(B16))) -> 4 | D16: Easy | E16: to grip, cut off, or tear with or as if with the teeth or jaws | F16: Nibble | G16: =IF(F16="","",LEN(F16)) -> 6 | H16: Small mouthful | I16: =IF(H16="","",LEN(H16)) -> 14 | K16: =IF(J16="","",LEN(J16))
A17: =IF(B17="","",ROW()-1) -> 16 | B17: blow | C17: =IF(B17="","",LEN(TRIM(B17))) -> 4 | D17: Easy | E17: exhale hard | G17: =IF(F17="","",LEN(F17)) | I17: =IF(H17="","",LEN(H17)) | K17: =IF(J17="","",LEN(J17))
A18: =IF(B18="","",ROW()-1) -> 17 | B18: blue | C18: =IF(B18="","",LEN(TRIM(B18))) -> 4 | D18: Easy | E18: blue color or pigment | F18: Sky color | G18: =IF(F18="","",LEN(F18)) -> 9 | H18: Feeling sad | I18: =IF(H18="","",LEN(H18)) -> 11 | K18: =IF(J18="","",LEN(J18))
A19: =IF(B19="","",ROW()-1) -> 18 | B19: boat | C19: =IF(B19="","",LEN(TRIM(B19))) -> 4 | D19: Easy | E19: a small vessel for travel on water | G19: =IF(F19="","",LEN(F19)) | I19: =IF(H19="","",LEN(H19)) | K19: =IF(J19="","",LEN(J19))
A20: =IF(B20="","",ROW()-1) -> 19 | B20: body | C20: =IF(B20="","",LEN(TRIM(B20))) -> 4 | D20: Easy | E20: the entire structure of an organism (an animal, plant, or human being) | F20: Torso and limbs | G20: =IF(F20="","",LEN(F20)) -> 15 | H20: Main part | I20: =IF(H20="","",LEN(H20)) -> 9 | K20: =IF(J20="","",LEN(J20))
A21: =IF(B21="","",ROW()-1) -> 20 | B21: book | C21: =IF(B21="","",LEN(TRIM(B21))) -> 4 | D21: Easy | E21: a written work or composition that has been published (printed on pages bound together) | G21: =IF(F21="","",LEN(F21)) | I21: =IF(H21="","",LEN(H21)) | K21: =IF(J21="","",LEN(J21))
A22: =IF(B22="","",ROW()-1) -> 21 | B22: boot | C22: =IF(B22="","",LEN(TRIM(B22))) -> 4 | D22: Easy | E22: footwear that covers the whole foot and lower leg | G22: =IF(F22="","",LEN(F22)) | I22: =IF(H22="","",LEN(H22)) | K22: =IF(J22="","",LEN(J22))
A23: =IF(B23="","",ROW()-1) -> 22 | B23: bore | C23: =IF(B23="","",LEN(TRIM(B23))) -> 4 | D23: Easy | E23: cause to be bored | F23: Dull person | G23: =IF(F23="","",LEN(F23)) -> 11 | H23: Tire out | I23: =IF(H23="","",LEN(H23)) -> 8 | K23: =IF(J23="","",LEN(J23))
A24: =IF(B24="","",ROW()-1) -> 23 | B24: both | C24: =IF(B24="","",LEN(TRIM(B24))) -> 4 | D24: Easy | E24: (used with count nouns) two considered together | G24: =IF(F24="","",LEN(F24)) | I24: =IF(H24="","",LEN(H24)) | K24: =IF(J24="","",LEN(J24))
A25: =IF(B25="","",ROW()-1) -> 24 | B25: bulk | C25: =IF(B25="","",LEN(TRIM(B25))) -> 4 | D25: Easy | E25: the property resulting from being or relating to the greater in number of two parts | G25: =IF(F25="","",LEN(F25)) | I25: =IF(H25="","",LEN(H25)) | K25: =IF(J25="","",LEN(J25))
A26: =IF(B26="","",ROW()-1) -> 25 | B26: bury | C26: =IF(B26="","",LEN(TRIM(B26))) -> 4 | D26: Easy | E26: cover from sight | G26: =IF(F26="","",LEN(F26)) | I26: =IF(H26="","",LEN(H26)) | K26: =IF(J26="","",LEN(J26))
A27: =IF(B27="","",ROW()-1) -> 26 | B27: busy | C27: =IF(B27="","",LEN(TRIM(B27))) -> 4 | D27: Easy | E27: actively or fully engaged or occupied | G27: =IF(F27="","",LEN(F27)) | I27: =IF(H27="","",LEN(H27)) | K27: =IF(J27="","",LEN(J27))
A28: =IF(B28="","",ROW()-1) -> 27 | B28: call | C28: =IF(B28="","",LEN(TRIM(B28))) -> 4 | D28: Easy | E28: assign a specified (usually proper) proper name to | G28: =IF(F28="","",LEN(F28)) | I28: =IF(H28="","",LEN(H28)) | K28: =IF(J28="","",LEN(J28))
A29: =IF(B29="","",ROW()-1) -> 28 | B29: card | C29: =IF(B29="","",LEN(TRIM(B29))) -> 4 | D29: Easy | E29: one of a set of small pieces of stiff paper marked in various ways and used for playing games or for telling fortunes | G29: =IF(F29="","",LEN(F29)) | I29: =IF(H29="","",LEN(H29)) | K29: =IF(J29="","",LEN(J29))
A30: =IF(B30="","",ROW()-1) -> 29 | B30: care | C30: =IF(B30="","",LEN(TRIM(B30))) -> 4 | D30: Easy | E30: the work of providing treatment for or attending to someone or something | G30: =IF(F30="","",LEN(F30)) | I30: =IF(H30="","",LEN(H30)) | K30: =IF(J30="","",LEN(J30))
A31: =IF(B31="","",ROW()-1) -> 30 | B31: case | C31: =IF(B31="","",LEN(TRIM(B31))) -> 4 | D31: Easy | E31: an occurrence of something | F31: Box | G31: =IF(F31="","",LEN(F31)) -> 3 | H31: Court matter | I31: =IF(H31="","",LEN(H31)) -> 12 | K31: =IF(J31="","",LEN(J31))
A32: =IF(B32="","",ROW()-1) -> 31 | B32: cell | C32: =IF(B32="","",LEN(TRIM(B32))) -> 4 | D32: Easy | E32: any small compartment | F32: Prison room | G32: =IF(F32="","",LEN(F32)) -> 11 | H32: Phone, for short | I32: =IF(H32="","",LEN(H32)) -> 16 | K32: =IF(J32="","",LEN(J32))
A33: =IF(B33="","",ROW()-1) -> 32 | B33: cent | C33: =IF(B33="","",LEN(TRIM(B33))) -> 4 | D33: Easy | E33: a fractional monetary unit of several countries | G33: =IF(F33="","",LEN(F33)) | I33: =IF(H33="","",LEN(H33)) | K33: =IF(J33="","",LEN(J33))
A34: =IF(B34="","",ROW()-1) -> 33 | B34: chip | C34: =IF(B34="","",LEN(TRIM(B34))) -> 4 | D34: Easy | E34: a small fragment of something broken off from the whole | G34: =IF(F34="","",LEN(F34)) | I34: =IF(H34="","",LEN(H34)) | K34: =IF(J34="","",LEN(J34))
A35: =IF(B35="","",ROW()-1) -> 34 | B35: city | C35: =IF(B35="","",LEN(TRIM(B35))) -> 4 | D35: Easy | E35: a large and densely populated urban area | G35: =IF(F35="","",LEN(F35)) | I35: =IF(H35="","",LEN(H35)) | K35: =IF(J35="","",LEN(J35))
A36: =IF(B36="","",ROW()-1) -> 35 | B36: club | C36: =IF(B36="","",LEN(TRIM(B36))) -> 4 | D36: Easy | E36: a team of professional baseball players who play and travel together | G36: =IF(F36="","",LEN(F36)) | I36: =IF(H36="","",LEN(H36)) | K36: =IF(J36="","",LEN(J36))
A37: =IF(B37="","",ROW()-1) -> 36 | B37: clue | C37: =IF(B37="","",LEN(TRIM(B37))) -> 4 | D37: Easy | E37: a slight indication | G37: =IF(F37="","",LEN(F37)) | I37: =IF(H37="","",LEN(H37)) | K37: =IF(J37="","",LEN(J37))
A38: =IF(B38="","",ROW()-1) -> 37 | B38: code | C38: =IF(B38="","",LEN(TRIM(B38))) -> 4 | D38: Easy | E38: a set of rules or principles or laws (especially written ones) | F38: Secret message | G38: =IF(F38="","",LEN(F38)) -> 14 | H38: Zip ___ | I38: =IF(H38="","",LEN(H38)) -> 7 | K38: =IF(J38="","",LEN(J38))
A39: =IF(B39="","",ROW()-1) -> 38 | B39: cold | C39: =IF(B39="","",LEN(TRIM(B39))) -> 4 | D39: Easy | E39: having a low or inadequate temperature or feeling a sensation of coldness or having been made cold by e.g. ice or refrigeration | F39: Chilly | G39: =IF(F39="","",LEN(F39)) -> 6 | H39: Common illness | I39: =IF(H39="","",LEN(H39)) -> 14 | K39: =IF(J39="","",LEN(J39))
A40: =IF(B40="","",ROW()-1) -> 39 | B40: come | C40: =IF(B40="","",LEN(TRIM(B40))) -> 4 | D40: Easy | E40: move toward, travel toward something or somebody or approach something or somebody | G40: =IF(F40="","",LEN(F40)) | I40: =IF(H40="","",LEN(H40)) | K40: =IF(J40="","",LEN(J40))
A41: =IF(B41="","",ROW()-1) -> 40 | B41: cope | C41: =IF(B41="","",LEN(TRIM(B41))) -> 4 | D41: Easy | E41: come to terms with | G41: =IF(F41="","",LEN(F41)) | I41: =IF(H41="","",LEN(H41)) | K41: =IF(J41="","",LEN(J41))
A42: =IF(B42="","",ROW()-1) -> 41 | B42: copy | C42: =IF(B42="","",LEN(TRIM(B42))) -> 4 | D42: Easy | E42: a reproduction of a written record (e.g. of a legal or school record) | G42: =IF(F42="","",LEN(F42)) | I42: =IF(H42="","",LEN(H42)) | K42: =IF(J42="","",LEN(J42))
A43: =IF(B43="","",ROW()-1) -> 42 | B43: core | C43: =IF(B43="","",LEN(TRIM(B43))) -> 4 | D43: Easy | E43: a small group of indispensable persons or things | F43: Apple center | G43: =IF(F43="","",LEN(F43)) -> 12 | H43: Heart | I43: =IF(H43="","",LEN(H43)) -> 5 | K43: =IF(J43="","",LEN(J43))
A44: =IF(B44="","",ROW()-1) -> 43 | B44: cost | C44: =IF(B44="","",LEN(TRIM(B44))) -> 4 | D44: Easy | E44: the total spent for goods or services including money and time and labor | G44: =IF(F44="","",LEN(F44)) | I44: =IF(H44="","",LEN(H44)) | K44: =IF(J44="","",LEN(J44))
A45: =IF(B45="","",ROW()-1) -> 44 | B45: cure | C45: =IF(B45="","",LEN(TRIM(B45))) -> 4 | D45: Easy | E45: provide a cure for, make healthy again | G45: =IF(F45="","",LEN(F45)) | I45: =IF(H45="","",LEN(H45)) | K45: =IF(J45="","",LEN(J45))
A46: =IF(B46="","",ROW()-1) -> 45 | B46: dare | C46: =IF(B46="","",LEN(TRIM(B46))) -> 4 | D46: Easy | E46: take upon oneself | F46: Challenge | G46: =IF(F46="","",LEN(F46)) -> 9 | H46: Have the nerve | I46: =IF(H46="","",LEN(H46)) -> 14 | K46: =IF(J46="","",LEN(J46))
A47: =IF(B47="","",ROW()-1) -> 46 | B47: dark | C47: =IF(B47="","",LEN(TRIM(B47))) -> 4 | D47: Easy | E47: absence of light or illumination | G47: =IF(F47="","",LEN(F47)) | I47: =IF(H47="","",LEN(H47)) | K47: =IF(J47="","",LEN(J47))
A48: =IF(B48="","",ROW()-1) -> 47 | B48: data | C48: =IF(B48="","",LEN(TRIM(B48))) -> 4 | D48: Easy | E48: a collection of facts from which conclusions may be drawn | F48: Facts | G48: =IF(F48="","",LEN(F48)) -> 5 | H48: Information | I48: =IF(H48="","",LEN(H48)) -> 11 | K48: =IF(J48="","",LEN(J48))
A49: =IF(B49="","",ROW()-1) -> 48 | B49: date | C49: =IF(B49="","",LEN(TRIM(B49))) -> 4 | D49: Easy | E49: the specified day of the month | G49: =IF(F49="","",LEN(F49)) | I49: =IF(H49="","",LEN(H49)) | K49: =IF(J49="","",LEN(J49))
A50: =IF(B50="","",ROW()-1) -> 49 | B50: deal | C50: =IF(B50="","",LEN(TRIM(B50))) -> 4 | D50: Easy | E50: act on verbally or in some form of artistic expression | F50: Bargain | G50: =IF(F50="","",LEN(F50)) -> 7 | H50: Hand out cards | I50: =IF(H50="","",LEN(H50)) -> 14 | K50: =IF(J50="","",LEN(J50))
A51: =IF(B51="","",ROW()-1) -> 50 | B51: dear | C51: =IF(B51="","",LEN(TRIM(B51))) -> 4 | D51: Easy | E51: dearly loved | F51: Beloved | G51: =IF(F51="","",LEN(F51)) -> 7 | H51: Costly | I51: =IF(H51="","",LEN(H51)) -> 6 | K51: =IF(J51="","",LEN(J51))
A52: =IF(B52="","",ROW()-1) -> 51 | B52: deep | C52: =IF(B52="","",LEN(TRIM(B52))) -> 4 | D52: Easy | E52: relatively deep or strong | F52: Not shallow | G52: =IF(F52="","",LEN(F52)) -> 11 | H52: Profound | I52: =IF(H52="","",LEN(H52)) -> 8 | K52: =IF(J52="","",LEN(J52))
A53: =IF(B53="","",ROW()-1) -> 52 | B53: desk | C53: =IF(B53="","",LEN(TRIM(B53))) -> 4 | D53: Easy | E53: a piece of furniture with a writing surface and usually drawers or other compartments | G53: =IF(F53="","",LEN(F53)) | I53: =IF(H53="","",LEN(H53)) | K53: =IF(J53="","",LEN(J53))
A54: =IF(B54="","",ROW()-1) -> 53 | B54: disc | C54: =IF(B54="","",LEN(TRIM(B54))) -> 4 | D54: Easy | E54: sound recording consisting of a disk with a continuous groove | F54: Flat round thing | G54: =IF(F54="","",LEN(F54)) -> 16 | H54: CD, e.g. | I54: =IF(H54="","",LEN(H54)) -> 8 | K54: =IF(J54="","",LEN(J54))
A55: =IF(B55="","",ROW()-1) -> 54 | B55: disk | C55: =IF(B55="","",LEN(TRIM(B55))) -> 4 | D55: Easy | E55: something with a round shape resembling a flat circular plate | G55: =IF(F55="","",LEN(F55)) | I55: =IF(H55="","",LEN(H55)) | K55: =IF(J55="","",LEN(J55))
A56: =IF(B56="","",ROW()-1) -> 55 | B56: door | C56: =IF(B56="","",LEN(TRIM(B56))) -> 4 | D56: Easy | E56: a swinging or sliding barrier that will close the entrance to a room or building or vehicle | G56: =IF(F56="","",LEN(F56)) | I56: =IF(H56="","",LEN(H56)) | K56: =IF(J56="","",LEN(J56))
A57: =IF(B57="","",ROW()-1) -> 56 | B57: down | C57: =IF(B57="","",LEN(TRIM(B57))) -> 4 | D57: Easy | E57: being or moving lower in position or less in some value | G57: =IF(F57="","",LEN(F57)) | I57: =IF(H57="","",LEN(H57)) | K57: =IF(J57="","",LEN(J57))
A58: =IF(B58="","",ROW()-1) -> 57 | B58: draw | C58: =IF(B58="","",LEN(TRIM(B58))) -> 4 | D58: Easy | E58: cause to move by pulling | G58: =IF(F58="","",LEN(F58)) | I58: =IF(H58="","",LEN(H58)) | K58: =IF(J58="","",LEN(J58))
A59: =IF(B59="","",ROW()-1) -> 58 | B59: drop | C59: =IF(B59="","",LEN(TRIM(B59))) -> 4 | D59: Easy | E59: let fall to the ground | G59: =IF(F59="","",LEN(F59)) | I59: =IF(H59="","",LEN(H59)) | K59: =IF(J59="","",LEN(J59))
A60: =IF(B60="","",ROW()-1) -> 59 | B60: dump | C60: =IF(B60="","",LEN(TRIM(B60))) -> 4 | D60: Easy | E60: throw away as refuse | G60: =IF(F60="","",LEN(F60)) | I60: =IF(H60="","",LEN(H60)) | K60: =IF(J60="","",LEN(J60))
A61: =IF(B61="","",ROW()-1) -> 60 | B61: duty | C61: =IF(B61="","",LEN(TRIM(B61))) -> 4 | D61: Easy | E61: the social force that binds you to the courses of action demanded by that force | G61: =IF(F61="","",LEN(F61)) | I61: =IF(H61="","",LEN(H61)) | K61: =IF(J61="","",LEN(J61))
A62: =IF(B62="","",ROW()-1) -> 61 | B62: each | C62: =IF(B62="","",LEN(TRIM(B62))) -> 4 | D62: Easy | E62: (used of count nouns) every one considered individually | F62: Every | G62: =IF(F62="","",LEN(F62)) -> 5 | H62: Apiece | I62: =IF(H62="","",LEN(H62)) -> 6 | K62: =IF(J62="","",LEN(J62))
A63: =IF(B63="","",ROW()-1) -> 62 | B63: ease | C63: =IF(B63="","",LEN(TRIM(B63))) -> 4 | D63: Easy | E63: move gently or carefully | F63: Comfort | G63: =IF(F63="","",LEN(F63)) -> 7 | H63: Relieve | I63: =IF(H63="","",LEN(H63)) -> 7 | K63: =IF(J63="","",LEN(J63))
A64: =IF(B64="","",ROW()-1) -> 63 | B64: east | C64: =IF(B64="","",LEN(TRIM(B64))) -> 4 | D64: Easy | E64: the cardinal compass point that is at 90 degrees | G64: =IF(F64="","",LEN(F64)) | I64: =IF(H64="","",LEN(H64)) | K64: =IF(J64="","",LEN(J64))
A65: =IF(B65="","",ROW()-1) -> 64 | B65: easy | C65: =IF(B65="","",LEN(TRIM(B65))) -> 4 | D65: Easy | E65: posing no difficulty | G65: =IF(F65="","",LEN(F65)) | I65: =IF(H65="","",LEN(H65)) | K65: =IF(J65="","",LEN(J65))
A66: =IF(B66="","",ROW()-1) -> 65 | B66: edge | C66: =IF(B66="","",LEN(TRIM(B66))) -> 4 | D66: Easy | E66: the boundary of a surface | F66: Rim | G66: =IF(F66="","",LEN(F66)) -> 3 | H66: Border | I66: =IF(H66="","",LEN(H66)) -> 6 | K66: =IF(J66="","",LEN(J66))
A67: =IF(B67="","",ROW()-1) -> 66 | B67: edit | C67: =IF(B67="","",LEN(TRIM(B67))) -> 4 | D67: Easy | E67: prepare for publication or presentation by correcting, revising, or adapting | F67: Revise | G67: =IF(F67="","",LEN(F67)) -> 6 | H67: Correct a text | I67: =IF(H67="","",LEN(H67)) -> 14 | K67: =IF(J67="","",LEN(J67))
A68: =IF(B68="","",ROW()-1) -> 67 | B68: even | C68: =IF(B68="","",LEN(TRIM(B68))) -> 4 | D68: Easy | E68: divisible by two | F68: Flat | G68: =IF(F68="","",LEN(F68)) -> 4 | H68: 2, 4 or 6 | I68: =IF(H68="","",LEN(H68)) -> 9 | K68: =IF(J68="","",LEN(J68))
A69: =IF(B69="","",ROW()-1) -> 68 | B69: ever | C69: =IF(B69="","",LEN(TRIM(B69))) -> 4 | D69: Easy | E69: at any time | F69: At any time | G69: =IF(F69="","",LEN(F69)) -> 11 | H69: Happily ___ after | I69: =IF(H69="","",LEN(H69)) -> 17 | K69: =IF(J69="","",LEN(J69))
A70: =IF(B70="","",ROW()-1) -> 69 | B70: face | C70: =IF(B70="","",LEN(TRIM(B70))) -> 4 | D70: Easy | E70: the front of the human head from the forehead to the chin and ear to ear | F70: Visage | G70: =IF(F70="","",LEN(F70)) -> 6 | H70: Clock front | I70: =IF(H70="","",LEN(H70)) -> 11 | K70: =IF(J70="","",LEN(J70))
A71: =IF(B71="","",ROW()-1) -> 70 | B71: fact | C71: =IF(B71="","",LEN(TRIM(B71))) -> 4 | D71: Easy | E71: a piece of information about circumstances that exist or events that have occurred | G71: =IF(F71="","",LEN(F71)) | I71: =IF(H71="","",LEN(H71)) | K71: =IF(J71="","",LEN(J71))
A72: =IF(B72="","",ROW()-1) -> 71 | B72: fail | C72: =IF(B72="","",LEN(TRIM(B72))) -> 4 | D72: Easy | E72: fail to do something | G72: =IF(F72="","",LEN(F72)) | I72: =IF(H72="","",LEN(H72)) | K72: =IF(J72="","",LEN(J72))
A73: =IF(B73="","",ROW()-1) -> 72 | B73: fair | C73: =IF(B73="","",LEN(TRIM(B73))) -> 4 | D73: Easy | E73: free from favoritism or self-interest or bias or deception | F73: Just | G73: =IF(F73="","",LEN(F73)) -> 4 | H73: County show | I73: =IF(H73="","",LEN(H73)) -> 11 | K73: =IF(J73="","",LEN(J73))
A74: =IF(B74="","",ROW()-1) -> 73 | B74: fall | C74: =IF(B74="","",LEN(TRIM(B74))) -> 4 | D74: Easy | E74: descend in free fall under the influence of gravity | F74: Autumn | G74: =IF(F74="","",LEN(F74)) -> 6 | H74: Tumble | I74: =IF(H74="","",LEN(H74)) -> 6 | K74: =IF(J74="","",LEN(J74))
A75: =IF(B75="","",ROW()-1) -> 74 | B75: farm | C75: =IF(B75="","",LEN(TRIM(B75))) -> 4 | D75: Easy | E75: workplace consisting of farm buildings and cultivated land as a unit | G75: =IF(F75="","",LEN(F75)) | I75: =IF(H75="","",LEN(H75)) | K75: =IF(J75="","",LEN(J75))
A76: =IF(B76="","",ROW()-1) -> 75 | B76: fast | C76: =IF(B76="","",LEN(TRIM(B76))) -> 4 | D76: Easy | E76: quickly or rapidly (often used as a combining form) | G76: =IF(F76="","",LEN(F76)) | I76: =IF(H76="","",LEN(H76)) | K76: =IF(J76="","",LEN(J76))
A77: =IF(B77="","",ROW()-1) -> 76 | B77: fate | C77: =IF(B77="","",LEN(TRIM(B77))) -> 4 | D77: Easy | E77: an event (or a course of events) that will inevitably happen in the future | F77: Destiny | G77: =IF(F77="","",LEN(F77)) -> 7 | H77: Fortune | I77: =IF(H77="","",LEN(H77)) -> 7 | K77: =IF(J77="","",LEN(J77))
A78: =IF(B78="","",ROW()-1) -> 77 | B78: fear | C78: =IF(B78="","",LEN(TRIM(B78))) -> 4 | D78: Easy | E78: be afraid or feel anxious or apprehensive about a possible or probable situation or event | G78: =IF(F78="","",LEN(F78)) | I78: =IF(H78="","",LEN(H78)) | K78: =IF(J78="","",LEN(J78))
A79: =IF(B79="","",ROW()-1) -> 78 | B79: feed | C79: =IF(B79="","",LEN(TRIM(B79))) -> 4 | D79: Easy | E79: provide as food | G79: =IF(F79="","",LEN(F79)) | I79: =IF(H79="","",LEN(H79)) | K79: =IF(J79="","",LEN(J79))
A80: =IF(B80="","",ROW()-1) -> 79 | B80: feel | C80: =IF(B80="","",LEN(TRIM(B80))) -> 4 | D80: Easy | E80: undergo an emotional sensation or be in a particular state of mind | G80: =IF(F80="","",LEN(F80)) | I80: =IF(H80="","",LEN(H80)) | K80: =IF(J80="","",LEN(J80))
A81: =IF(B81="","",ROW()-1) -> 80 | B81: fell | C81: =IF(B81="","",LEN(TRIM(B81))) -> 4 | D81: Easy | E81: cause to fall by or as if by delivering a blow | G81: =IF(F81="","",LEN(F81)) | I81: =IF(H81="","",LEN(H81)) | K81: =IF(J81="","",LEN(J81))
A82: =IF(B82="","",ROW()-1) -> 81 | B82: felt | C82: =IF(B82="","",LEN(TRIM(B82))) -> 4 | D82: Easy | E82: a fabric made of compressed matted animal fibers | G82: =IF(F82="","",LEN(F82)) | I82: =IF(H82="","",LEN(H82)) | K82: =IF(J82="","",LEN(J82))
A83: =IF(B83="","",ROW()-1) -> 82 | B83: file | C83: =IF(B83="","",LEN(TRIM(B83))) -> 4 | D83: Easy | E83: record in a public office or in a court of law | F83: Folder | G83: =IF(F83="","",LEN(F83)) -> 6 | H83: Nail tool | I83: =IF(H83="","",LEN(H83)) -> 9 | K83: =IF(J83="","",LEN(J83))
A84: =IF(B84="","",ROW()-1) -> 83 | B84: fill | C84: =IF(B84="","",LEN(TRIM(B84))) -> 4 | D84: Easy | E84: make full, also in a metaphorical sense | G84: =IF(F84="","",LEN(F84)) | I84: =IF(H84="","",LEN(H84)) | K84: =IF(J84="","",LEN(J84))
A85: =IF(B85="","",ROW()-1) -> 84 | B85: film | C85: =IF(B85="","",LEN(TRIM(B85))) -> 4 | D85: Easy | E85: a form of entertainment that enacts a story by sound and a sequence of images giving the illusion of continuous movement | G85: =IF(F85="","",LEN(F85)) | I85: =IF(H85="","",LEN(H85)) | K85: =IF(J85="","",LEN(J85))
A86: =IF(B86="","",ROW()-1) -> 85 | B86: find | C86: =IF(B86="","",LEN(TRIM(B86))) -> 4 | D86: Easy | E86: come upon, as if by accident | G86: =IF(F86="","",LEN(F86)) | I86: =IF(H86="","",LEN(H86)) | K86: =IF(J86="","",LEN(J86))
A87: =IF(B87="","",ROW()-1) -> 86 | B87: fine | C87: =IF(B87="","",LEN(TRIM(B87))) -> 4 | D87: Easy | E87: being satisfactory or in satisfactory condition | G87: =IF(F87="","",LEN(F87)) | I87: =IF(H87="","",LEN(H87)) | K87: =IF(J87="","",LEN(J87))
A88: =IF(B88="","",ROW()-1) -> 87 | B88: fire | C88: =IF(B88="","",LEN(TRIM(B88))) -> 4 | D88: Easy | E88: start firing a weapon | F88: Flames | G88: =IF(F88="","",LEN(F88)) -> 6 | H88: Dismiss from a job | I88: =IF(H88="","",LEN(H88)) -> 18 | K88: =IF(J88="","",LEN(J88))
A89: =IF(B89="","",ROW()-1) -> 88 | B89: firm | C89: =IF(B89="","",LEN(TRIM(B89))) -> 4 | D89: Easy | E89: marked by firm determination or resolution | G89: =IF(F89="","",LEN(F89)) | I89: =IF(H89="","",LEN(H89)) | K89: =IF(J89="","",LEN(J89))
A90: =IF(B90="","",ROW()-1) -> 89 | B90: fish | C90: =IF(B90="","",LEN(TRIM(B90))) -> 4 | D90: Easy | E90: any of various mostly cold-blooded aquatic vertebrates usually having scales and breathing through gills | G90: =IF(F90="","",LEN(F90)) | I90: =IF(H90="","",LEN(H90)) | K90: =IF(J90="","",LEN(J90))
A91: =IF(B91="","",ROW()-1) -> 90 | B91: five | C91: =IF(B91="","",LEN(TRIM(B91))) -> 4 | D91: Easy | E91: the cardinal number that is the sum of four and one | G91: =IF(F91="","",LEN(F91)) | I91: =IF(H91="","",LEN(H91)) | K91: =IF(J91="","",LEN(J91))
A92: =IF(B92="","",ROW()-1) -> 91 | B92: flag | C92: =IF(B92="","",LEN(TRIM(B92))) -> 4 | D92: Easy | E92: emblem usually consisting of a rectangular piece of cloth of distinctive design | G92: =IF(F92="","",LEN(F92)) | I92: =IF(H92="","",LEN(H92)) | K92: =IF(J92="","",LEN(J92))
A93: =IF(B93="","",ROW()-1) -> 92 | B93: flat | C93: =IF(B93="","",LEN(TRIM(B93))) -> 4 | D93: Easy | E93: having a surface without slope, tilt in which no part is higher or lower than another | G93: =IF(F93="","",LEN(F93)) | I93: =IF(H93="","",LEN(H93)) | K93: =IF(J93="","",LEN(J93))
A94: =IF(B94="","",ROW()-1) -> 93 | B94: flow | C94: =IF(B94="","",LEN(TRIM(B94))) -> 4 | D94: Easy | E94: the motion characteristic of fluids (liquids or gases) | G94: =IF(F94="","",LEN(F94)) | I94: =IF(H94="","",LEN(H94)) | K94: =IF(J94="","",LEN(J94))
A95: =IF(B95="","",ROW()-1) -> 94 | B95: folk | C95: =IF(B95="","",LEN(TRIM(B95))) -> 4 | D95: Easy | E95: people in general (often used in the plural) | G95: =IF(F95="","",LEN(F95)) | I95: =IF(H95="","",LEN(H95)) | K95: =IF(J95="","",LEN(J95))
A96: =IF(B96="","",ROW()-1) -> 95 | B96: food | C96: =IF(B96="","",LEN(TRIM(B96))) -> 4 | D96: Easy | E96: any substance that can be metabolized by an animal to give energy and build tissue | G96: =IF(F96="","",LEN(F96)) | I96: =IF(H96="","",LEN(H96)) | K96: =IF(J96="","",LEN(J96))
A97: =IF(B97="","",ROW()-1) -> 96 | B97: foot | C97: =IF(B97="","",LEN(TRIM(B97))) -> 4 | D97: Easy | E97: the part of the leg of a human being below the ankle joint | G97: =IF(F97="","",LEN(F97)) | I97: =IF(H97="","",LEN(H97)) | K97: =IF(J97="","",LEN(J97))
A98: =IF(B98="","",ROW()-1) -> 97 | B98: form | C98: =IF(B98="","",LEN(TRIM(B98))) -> 4 | D98: Easy | E98: the phonological or orthographic sound or appearance of a word that can be used to describe or identify something | F98: Shape | G98: =IF(F98="","",LEN(F98)) -> 5 | H98: Paper to fill in | I98: =IF(H98="","",LEN(H98)) -> 16 | K98: =IF(J98="","",LEN(J98))
A99: =IF(B99="","",ROW()-1) -> 98 | B99: four | C99: =IF(B99="","",LEN(TRIM(B99))) -> 4 | D99: Easy | E99: the cardinal number that is the sum of three and one | G99: =IF(F99="","",LEN(F99)) | I99: =IF(H99="","",LEN(H99)) | K99: =IF(J99="","",LEN(J99))
A100: =IF(B100="","",ROW()-1) -> 99 | B100: free | C100: =IF(B100="","",LEN(TRIM(B100))) -> 4 | D100: Easy | E100: grant freedom to | F100: No cost | G100: =IF(F100="","",LEN(F100)) -> 7 | H100: Released | I100: =IF(H100="","",LEN(H100)) -> 8 | K100: =IF(J100="","",LEN(J100))
...

Sheet 5 letters
A1: ID | B1: Word | C1: Letters | D1: Difficulty | E1: Definition | F1: Clue 1 | G1: Len | H1: Clue 2 | I1: Len | J1: Clue 3 | K1: Len | L1: Notes
A2: =IF(B2="","",ROW()-1) -> 1 | B2: about | C2: =IF(B2="","",LEN(TRIM(B2))) -> 5 | D2: Easy | E2: (of quantities) imprecise but fairly close to correct | G2: =IF(F2="","",LEN(F2)) | I2: =IF(H2="","",LEN(H2)) | K2: =IF(J2="","",LEN(J2))
A3: =IF(B3="","",ROW()-1) -> 2 | B3: above | C3: =IF(B3="","",LEN(TRIM(B3))) -> 5 | D3: Easy | E3: at an earlier place | G3: =IF(F3="","",LEN(F3)) | I3: =IF(H3="","",LEN(H3)) | K3: =IF(J3="","",LEN(J3))
A4: =IF(B4="","",ROW()-1) -> 3 | B4: abuse | C4: =IF(B4="","",LEN(TRIM(B4))) -> 5 | D4: Easy | E4: treat badly | F4: Treat badly | G4: =IF(F4="","",LEN(F4)) -> 11 | H4: Misuse | I4: =IF(H4="","",LEN(H4)) -> 6 | K4: =IF(J4="","",LEN(J4))
A5: =IF(B5="","",ROW()-1) -> 4 | B5: admit | C5: =IF(B5="","",LEN(TRIM(B5))) -> 5 | D5: Easy | E5: declare to be true or admit the existence or reality or truth of | G5: =IF(F5="","",LEN(F5)) | I5: =IF(H5="","",LEN(H5)) | K5: =IF(J5="","",LEN(J5))
A6: =IF(B6="","",ROW()-1) -> 5 | B6: adopt | C6: =IF(B6="","",LEN(TRIM(B6))) -> 5 | D6: Easy | E6: choose and follow | G6: =IF(F6="","",LEN(F6)) | I6: =IF(H6="","",LEN(H6)) | K6: =IF(J6="","",LEN(J6))
A7: =IF(B7="","",ROW()-1) -> 6 | B7: after | C7: =IF(B7="","",LEN(TRIM(B7))) -> 5 | D7: Easy | E7: happening at a time subsequent to a reference time | G7: =IF(F7="","",LEN(F7)) | I7: =IF(H7="","",LEN(H7)) | K7: =IF(J7="","",LEN(J7))
A8: =IF(B8="","",ROW()-1) -> 7 | B8: again | C8: =IF(B8="","",LEN(TRIM(B8))) -> 5 | D8: Easy | E8: anew | F8: Once more | G8: =IF(F8="","",LEN(F8)) -> 9 | H8: One more time | I8: =IF(H8="","",LEN(H8)) -> 13 | K8: =IF(J8="","",LEN(J8))
A9: =IF(B9="","",ROW()-1) -> 8 | B9: agree | C9: =IF(B9="","",LEN(TRIM(B9))) -> 5 | D9: Easy | E9: be in accord | G9: =IF(F9="","",LEN(F9)) | I9: =IF(H9="","",LEN(H9)) | K9: =IF(J9="","",LEN(J9))
A10: =IF(B10="","",ROW()-1) -> 9 | B10: ahead | C10: =IF(B10="","",LEN(TRIM(B10))) -> 5 | D10: Easy | E10: at or in the front | F10: In front | G10: =IF(F10="","",LEN(F10)) -> 8 | H10: Go ___ (proceed) | I10: =IF(H10="","",LEN(H10)) -> 16 | K10: =IF(J10="","",LEN(J10))
A11: =IF(B11="","",ROW()-1) -> 10 | B11: alarm | C11: =IF(B11="","",LEN(TRIM(B11))) -> 5 | D11: Easy | E11: fear resulting from the awareness of danger | G11: =IF(F11="","",LEN(F11)) | I11: =IF(H11="","",LEN(H11)) | K11: =IF(J11="","",LEN(J11))
A12: =IF(B12="","",ROW()-1) -> 11 | B12: album | C12: =IF(B12="","",LEN(TRIM(B12))) -> 5 | D12: Easy | E12: one or more recordings issued together | G12: =IF(F12="","",LEN(F12)) | I12: =IF(H12="","",LEN(H12)) | K12: =IF(J12="","",LEN(J12))
A13: =IF(B13="","",ROW()-1) -> 12 | B13: alive | C13: =IF(B13="","",LEN(TRIM(B13))) -> 5 | D13: Easy | E13: possessing life | G13: =IF(F13="","",LEN(F13)) | I13: =IF(H13="","",LEN(H13)) | K13: =IF(J13="","",LEN(J13))
A14: =IF(B14="","",ROW()-1) -> 13 | B14: allow | C14: =IF(B14="","",LEN(TRIM(B14))) -> 5 | D14: Easy | E14: make it possible through a specific action or lack of action for something to happen | G14: =IF(F14="","",LEN(F14)) | I14: =IF(H14="","",LEN(H14)) | K14: =IF(J14="","",LEN(J14))
A15: =IF(B15="","",ROW()-1) -> 14 | B15: alone | C15: =IF(B15="","",LEN(TRIM(B15))) -> 5 | D15: Easy | E15: isolated from others | G15: =IF(F15="","",LEN(F15)) | I15: =IF(H15="","",LEN(H15)) | K15: =IF(J15="","",LEN(J15))
A16: =IF(B16="","",ROW()-1) -> 15 | B16: along | C16: =IF(B16="","",LEN(TRIM(B16))) -> 5 | D16: Easy | E16: with a forward motion | G16: =IF(F16="","",LEN(F16)) | I16: =IF(H16="","",LEN(H16)) | K16: =IF(J16="","",LEN(J16))
A17: =IF(B17="","",ROW()-1) -> 16 | B17: alter | C17: =IF(B17="","",LEN(TRIM(B17))) -> 5 | D17: Easy | E17: cause to change | G17: =IF(F17="","",LEN(F17)) | I17: =IF(H17="","",LEN(H17)) | K17: =IF(J17="","",LEN(J17))
A18: =IF(B18="","",ROW()-1) -> 17 | B18: amuse | C18: =IF(B18="","",LEN(TRIM(B18))) -> 5 | D18: Easy | E18: occupy in an agreeable, entertaining or pleasant fashion | G18: =IF(F18="","",LEN(F18)) | I18: =IF(H18="","",LEN(H18)) | K18: =IF(J18="","",LEN(J18))
A19: =IF(B19="","",ROW()-1) -> 18 | B19: angle | C19: =IF(B19="","",LEN(TRIM(B19))) -> 5 | D19: Easy | E19: the space between two lines or planes that intersect | F19: Corner measure | G19: =IF(F19="","",LEN(F19)) -> 14 | H19: Point of view | I19: =IF(H19="","",LEN(H19)) -> 13 | K19: =IF(J19="","",LEN(J19))
A20: =IF(B20="","",ROW()-1) -> 19 | B20: angry | C20: =IF(B20="","",LEN(TRIM(B20))) -> 5 | D20: Easy | E20: feeling or showing anger | G20: =IF(F20="","",LEN(F20)) | I20: =IF(H20="","",LEN(H20)) | K20: =IF(J20="","",LEN(J20))
A21: =IF(B21="","",ROW()-1) -> 20 | B21: annoy | C21: =IF(B21="","",LEN(TRIM(B21))) -> 5 | D21: Easy | E21: cause annoyance in | G21: =IF(F21="","",LEN(F21)) | I21: =IF(H21="","",LEN(H21)) | K21: =IF(J21="","",LEN(J21))
A22: =IF(B22="","",ROW()-1) -> 21 | B22: apart | C22: =IF(B22="","",LEN(TRIM(B22))) -> 5 | D22: Easy | E22: separated or at a distance in place or position or time | G22: =IF(F22="","",LEN(F22)) | I22: =IF(H22="","",LEN(H22)) | K22: =IF(J22="","",LEN(J22))
A23: =IF(B23="","",ROW()-1) -> 22 | B23: apple | C23: =IF(B23="","",LEN(TRIM(B23))) -> 5 | D23: Easy | E23: fruit with red or yellow or green skin and sweet to tart crisp whitish flesh | G23: =IF(F23="","",LEN(F23)) | I23: =IF(H23="","",LEN(H23)) | K23: =IF(J23="","",LEN(J23))
A24: =IF(B24="","",ROW()-1) -> 23 | B24: apply | C24: =IF(B24="","",LEN(TRIM(B24))) -> 5 | D24: Easy | E24: put into service | G24: =IF(F24="","",LEN(F24)) | I24: =IF(H24="","",LEN(H24)) | K24: =IF(J24="","",LEN(J24))
A25: =IF(B25="","",ROW()-1) -> 24 | B25: argue | C25: =IF(B25="","",LEN(TRIM(B25))) -> 5 | D25: Easy | E25: present reasons and arguments | G25: =IF(F25="","",LEN(F25)) | I25: =IF(H25="","",LEN(H25)) | K25: =IF(J25="","",LEN(J25))
A26: =IF(B26="","",ROW()-1) -> 25 | B26: arise | C26: =IF(B26="","",LEN(TRIM(B26))) -> 5 | D26: Easy | E26: come into existence | F26: Get up | G26: =IF(F26="","",LEN(F26)) -> 6 | H26: Come up | I26: =IF(H26="","",LEN(H26)) -> 7 | K26: =IF(J26="","",LEN(J26))
A27: =IF(B27="","",ROW()-1) -> 26 | B27: aside | C27: =IF(B27="","",LEN(TRIM(B27))) -> 5 | D27: Easy | E27: on or to one side | G27: =IF(F27="","",LEN(F27)) | I27: =IF(H27="","",LEN(H27)) | K27: =IF(J27="","",LEN(J27))
A28: =IF(B28="","",ROW()-1) -> 27 | B28: avoid | C28: =IF(B28="","",LEN(TRIM(B28))) -> 5 | D28: Easy | E28: stay clear from | G28: =IF(F28="","",LEN(F28)) | I28: =IF(H28="","",LEN(H28)) | K28: =IF(J28="","",LEN(J28))
A29: =IF(B29="","",ROW()-1) -> 28 | B29: awake | C29: =IF(B29="","",LEN(TRIM(B29))) -> 5 | D29: Easy | E29: stop sleeping | G29: =IF(F29="","",LEN(F29)) | I29: =IF(H29="","",LEN(H29)) | K29: =IF(J29="","",LEN(J29))
A30: =IF(B30="","",ROW()-1) -> 29 | B30: award | C30: =IF(B30="","",LEN(TRIM(B30))) -> 5 | D30: Easy | E30: a grant made by a law court | F30: Prize | G30: =IF(F30="","",LEN(F30)) -> 5 | H30: Trophy | I30: =IF(H30="","",LEN(H30)) -> 6 | K30: =IF(J30="","",LEN(J30))
A31: =IF(B31="","",ROW()-1) -> 30 | B31: aware | C31: =IF(B31="","",LEN(TRIM(B31))) -> 5 | D31: Easy | E31: (sometimes followed by `of') having or showing knowledge or understanding or realization or perception | F31: Knowing | G31: =IF(F31="","",LEN(F31)) -> 7 | H31: Conscious | I31: =IF(H31="","",LEN(H31)) -> 9 | K31: =IF(J31="","",LEN(J31))
A32: =IF(B32="","",ROW()-1) -> 31 | B32: awful | C32: =IF(B32="","",LEN(TRIM(B32))) -> 5 | D32: Easy | E32: exceptionally bad or displeasing | G32: =IF(F32="","",LEN(F32)) | I32: =IF(H32="","",LEN(H32)) | K32: =IF(J32="","",LEN(J32))
A33: =IF(B33="","",ROW()-1) -> 32 | B33: basic | C33: =IF(B33="","",LEN(TRIM(B33))) -> 5 | D33: Easy | E33: pertaining to or constituting a base or basis | G33: =IF(F33="","",LEN(F33)) | I33: =IF(H33="","",LEN(H33)) | K33: =IF(J33="","",LEN(J33))
A34: =IF(B34="","",ROW()-1) -> 33 | B34: basis | C34: =IF(B34="","",LEN(TRIM(B34))) -> 5 | D34: Easy | E34: a relation that provides the foundation for something | F34: Foundation | G34: =IF(F34="","",LEN(F34)) -> 10 | H34: Grounds | I34: =IF(H34="","",LEN(H34)) -> 7 | K34: =IF(J34="","",LEN(J34))
A35: =IF(B35="","",ROW()-1) -> 34 | B35: begin | C35: =IF(B35="","",LEN(TRIM(B35))) -> 5 | D35: Easy | E35: take the first step or steps in carrying out an action | G35: =IF(F35="","",LEN(F35)) | I35: =IF(H35="","",LEN(H35)) | K35: =IF(J35="","",LEN(J35))
A36: =IF(B36="","",ROW()-1) -> 35 | B36: being | C36: =IF(B36="","",LEN(TRIM(B36))) -> 5 | D36: Easy | E36: the state or fact of existing | G36: =IF(F36="","",LEN(F36)) | I36: =IF(H36="","",LEN(H36)) | K36: =IF(J36="","",LEN(J36))
A37: =IF(B37="","",ROW()-1) -> 36 | B37: below | C37: =IF(B37="","",LEN(TRIM(B37))) -> 5 | D37: Easy | E37: in or to a place that is lower | F37: Under | G37: =IF(F37="","",LEN(F37)) -> 5 | H37: Beneath | I37: =IF(H37="","",LEN(H37)) -> 7 | K37: =IF(J37="","",LEN(J37))
A38: =IF(B38="","",ROW()-1) -> 37 | B38: black | C38: =IF(B38="","",LEN(TRIM(B38))) -> 5 | D38: Easy | E38: being of the achromatic color of maximum darkness | G38: =IF(F38="","",LEN(F38)) | I38: =IF(H38="","",LEN(H38)) | K38: =IF(J38="","",LEN(J38))
A39: =IF(B39="","",ROW()-1) -> 38 | B39: blame | C39: =IF(B39="","",LEN(TRIM(B39))) -> 5 | D39: Easy | E39: put or pin the blame on | G39: =IF(F39="","",LEN(F39)) | I39: =IF(H39="","",LEN(H39)) | K39: =IF(J39="","",LEN(J39))
A40: =IF(B40="","",ROW()-1) -> 39 | B40: blank | C40: =IF(B40="","",LEN(TRIM(B40))) -> 5 | D40: Easy | E40: (of a surface) not written or printed on | G40: =IF(F40="","",LEN(F40)) | I40: =IF(H40="","",LEN(H40)) | K40: =IF(J40="","",LEN(J40))
A41: =IF(B41="","",ROW()-1) -> 40 | B41: block | C41: =IF(B41="","",LEN(TRIM(B41))) -> 5 | D41: Easy | E41: a solid piece of something (usually having flat rectangular sides) | G41: =IF(F41="","",LEN(F41)) | I41: =IF(H41="","",LEN(H41)) | K41: =IF(J41="","",LEN(J41))
A42: =IF(B42="","",ROW()-1) -> 41 | B42: board | C42: =IF(B42="","",LEN(TRIM(B42))) -> 5 | D42: Easy | E42: a committee having supervisory powers | G42: =IF(F42="","",LEN(F42)) | I42: =IF(H42="","",LEN(H42)) | K42: =IF(J42="","",LEN(J42))
A43: =IF(B43="","",ROW()-1) -> 42 | B43: bound | C43: =IF(B43="","",LEN(TRIM(B43))) -> 5 | D43: Easy | E43: confined by bonds | G43: =IF(F43="","",LEN(F43)) | I43: =IF(H43="","",LEN(H43)) | K43: =IF(J43="","",LEN(J43))
A44: =IF(B44="","",ROW()-1) -> 43 | B44: brand | C44: =IF(B44="","",LEN(TRIM(B44))) -> 5 | D44: Easy | E44: a name given to a product or service | G44: =IF(F44="","",LEN(F44)) | I44: =IF(H44="","",LEN(H44)) | K44: =IF(J44="","",LEN(J44))
A45: =IF(B45="","",ROW()-1) -> 44 | B45: break | C45: =IF(B45="","",LEN(TRIM(B45))) -> 5 | D45: Easy | E45: terminate | G45: =IF(F45="","",LEN(F45)) | I45: =IF(H45="","",LEN(H45)) | K45: =IF(J45="","",LEN(J45))
A46: =IF(B46="","",ROW()-1) -> 45 | B46: brief | C46: =IF(B46="","",LEN(TRIM(B46))) -> 5 | D46: Easy | E46: of short duration or distance | G46: =IF(F46="","",LEN(F46)) | I46: =IF(H46="","",LEN(H46)) | K46: =IF(J46="","",LEN(J46))
A47: =IF(B47="","",ROW()-1) -> 46 | B47: bring | C47: =IF(B47="","",LEN(TRIM(B47))) -> 5 | D47: Easy | E47: take something or somebody with oneself somewhere | G47: =IF(F47="","",LEN(F47)) | I47: =IF(H47="","",LEN(H47)) | K47: =IF(J47="","",LEN(J47))
A48: =IF(B48="","",ROW()-1) -> 47 | B48: brown | C48: =IF(B48="","",LEN(TRIM(B48))) -> 5 | D48: Easy | E48: an orange of low brightness and saturation | G48: =IF(F48="","",LEN(F48)) | I48: =IF(H48="","",LEN(H48)) | K48: =IF(J48="","",LEN(J48))
A49: =IF(B49="","",ROW()-1) -> 48 | B49: build | C49: =IF(B49="","",LEN(TRIM(B49))) -> 5 | D49: Easy | E49: make by combining materials and parts | G49: =IF(F49="","",LEN(F49)) | I49: =IF(H49="","",LEN(H49)) | K49: =IF(J49="","",LEN(J49))
... A51: =IF(B51="","",ROW()-1) -> 50 | B51: carry | C51: =IF(B51="","",LEN(TRIM(B51))) -> 5 | D51: Easy | E51: move while supporting, either in a vehicle or in one's hands or on one's body | G51: =IF(F51="","",LEN(F51)) | I51: =IF(H51="","",LEN(H51)) | K51: =IF(J51="","",LEN(J51))
A52: =IF(B52="","",ROW()-1) -> 51 | B52: catch | C52: =IF(B52="","",LEN(TRIM(B52))) -> 5 | D52: Easy | E52: discover or come upon accidentally, suddenly, or unexpectedly | F52: Grab | G52: =IF(F52="","",LEN(F52)) -> 4 | H52: Fish haul | I52: =IF(H52="","",LEN(H52)) -> 9 | K52: =IF(J52="","",LEN(J52))
A53: =IF(B53="","",ROW()-1) -> 52 | B53: cause | C53: =IF(B53="","",LEN(TRIM(B53))) -> 5 | D53: Easy | E53: events that provide the generative force that is the origin of something | G53: =IF(F53="","",LEN(F53)) | I53: =IF(H53="","",LEN(H53)) | K53: =IF(J53="","",LEN(J53))
A54: =IF(B54="","",ROW()-1) -> 53 | B54: cease | C54: =IF(B54="","",LEN(TRIM(B54))) -> 5 | D54: Easy | E54: put an end to a state or an activity | F54: Stop | G54: =IF(F54="","",LEN(F54)) -> 4 | H54: Halt | I54: =IF(H54="","",LEN(H54)) -> 4 | K54: =IF(J54="","",LEN(J54))
A55: =IF(B55="","",ROW()-1) -> 54 | B55: chain | C55: =IF(B55="","",LEN(TRIM(B55))) -> 5 | D55: Easy | E55: a series of things depending on each other as if linked together | G55: =IF(F55="","",LEN(F55)) | I55: =IF(H55="","",LEN(H55)) | K55: =IF(J55="","",LEN(J55))
A56: =IF(B56="","",ROW()-1) -> 55 | B56: chair | C56: =IF(B56="","",LEN(TRIM(B56))) -> 5 | D56: Easy | E56: a seat for one person, with a support for the back | F56: Seat with a back | G56: =IF(F56="","",LEN(F56)) -> 16 | H56: Meeting head | I56: =IF(H56="","",LEN(H56)) -> 12 | K56: =IF(J56="","",LEN(J56))
A57: =IF(B57="","",ROW()-1) -> 56 | B57: chaos | C57: =IF(B57="","",LEN(TRIM(B57))) -> 5 | D57: Easy | E57: a state of extreme confusion and disorder | G57: =IF(F57="","",LEN(F57)) | I57: =IF(H57="","",LEN(H57)) | K57: =IF(J57="","",LEN(J57))
A58: =IF(B58="","",ROW()-1) -> 57 | B58: cheap | C58: =IF(B58="","",LEN(TRIM(B58))) -> 5 | D58: Easy | E58: relatively low in price or charging low prices | G58: =IF(F58="","",LEN(F58)) | I58: =IF(H58="","",LEN(H58)) | K58: =IF(J58="","",LEN(J58))
A59: =IF(B59="","",ROW()-1) -> 58 | B59: check | C59: =IF(B59="","",LEN(TRIM(B59))) -> 5 | D59: Easy | E59: examine so as to determine accuracy, quality, or condition | G59: =IF(F59="","",LEN(F59)) | I59: =IF(H59="","",LEN(H59)) | K59: =IF(J59="","",LEN(J59))
A60: =IF(B60="","",ROW()-1) -> 59 | B60: child | C60: =IF(B60="","",LEN(TRIM(B60))) -> 5 | D60: Easy | E60: a young person of either sex | G60: =IF(F60="","",LEN(F60)) | I60: =IF(H60="","",LEN(H60)) | K60: =IF(J60="","",LEN(J60))
A61: =IF(B61="","",ROW()-1) -> 60 | B61: claim | C61: =IF(B61="","",LEN(TRIM(B61))) -> 5 | D61: Easy | E61: an assertion of a right (as to money or property) | F61: State as fact | G61: =IF(F61="","",LEN(F61)) -> 13 | H61: Insurance request | I61: =IF(H61="","",LEN(H61)) -> 17 | K61: =IF(J61="","",LEN(J61))
A62: =IF(B62="","",ROW()-1) -> 61 | B62: class | C62: =IF(B62="","",LEN(TRIM(B62))) -> 5 | D62: Easy | E62: a collection of things sharing a common attribute | G62: =IF(F62="","",LEN(F62)) | I62: =IF(H62="","",LEN(H62)) | K62: =IF(J62="","",LEN(J62))
A63: =IF(B63="","",ROW()-1) -> 62 | B63: clean | C63: =IF(B63="","",LEN(TRIM(B63))) -> 5 | D63: Easy | E63: free from dirt or impurities | F63: Spotless | G63: =IF(F63="","",LEN(F63)) -> 8 | H63: Wash | I63: =IF(H63="","",LEN(H63)) -> 4 | K63: =IF(J63="","",LEN(J63))
A64: =IF(B64="","",ROW()-1) -> 63 | B64: clear | C64: =IF(B64="","",LEN(TRIM(B64))) -> 5 | D64: Easy | E64: rid of obstructions | G64: =IF(F64="","",LEN(F64)) | I64: =IF(H64="","",LEN(H64)) | K64: =IF(J64="","",LEN(J64))
A65: =IF(B65="","",ROW()-1) -> 64 | B65: clock | C65: =IF(B65="","",LEN(TRIM(B65))) -> 5 | D65: Easy | E65: a timepiece that shows the time of day | G65: =IF(F65="","",LEN(F65)) | I65: =IF(H65="","",LEN(H65)) | K65: =IF(J65="","",LEN(J65))
A66: =IF(B66="","",ROW()-1) -> 65 | B66: close | C66: =IF(B66="","",LEN(TRIM(B66))) -> 5 | D66: Easy | E66: at or within a short distance in space or time or having elements near each other | F66: Shut | G66: =IF(F66="","",LEN(F66)) -> 4 | H66: Near | I66: =IF(H66="","",LEN(H66)) -> 4 | K66: =IF(J66="","",LEN(J66))
A67: =IF(B67="","",ROW()-1) -> 66 | B67: color | C67: =IF(B67="","",LEN(TRIM(B67))) -> 5 | D67: Easy | E67: a visual attribute of things that results from the light they emit or transmit or reflect | F67: Red or blue, e.g. | G67: =IF(F67="","",LEN(F67)) -> 17 | H67: Hue | I67: =IF(H67="","",LEN(H67)) -> 3 | K67: =IF(J67="","",LEN(J67))
A68: =IF(B68="","",ROW()-1) -> 67 | B68: count | C68: =IF(B68="","",LEN(TRIM(B68))) -> 5 | D68: Easy | E68: determine the number or amount of | G68: =IF(F68="","",LEN(F68)) | I68: =IF(H68="","",LEN(H68)) | K68: =IF(J68="","",LEN(J68))
A69: =IF(B69="","",ROW()-1) -> 68 | B69: court | C69: =IF(B69="","",LEN(TRIM(B69))) -> 5 | D69: Easy | E69: an assembly (including one or more judges) to conduct judicial business | F69: Tennis area | G69: =IF(F69="","",LEN(F69)) -> 11 | H69: Judge's room | I69: =IF(H69="","",LEN(H69)) -> 12 | K69: =IF(J69="","",LEN(J69))
A70: =IF(B70="","",ROW()-1) -> 69 | B70: cover | C70: =IF(B70="","",LEN(TRIM(B70))) -> 5 | D70: Easy | E70: provide with a covering or cause to be covered | G70: =IF(F70="","",LEN(F70)) | I70: =IF(H70="","",LEN(H70)) | K70: =IF(J70="","",LEN(J70))
A71: =IF(B71="","",ROW()-1) -> 70 | B71: crash | C71: =IF(B71="","",LEN(TRIM(B71))) -> 5 | D71: Easy | E71: fall or come down violently | G71: =IF(F71="","",LEN(F71)) | I71: =IF(H71="","",LEN(H71)) | K71: =IF(J71="","",LEN(J71))
A72: =IF(B72="","",ROW()-1) -> 71 | B72: crazy | C72: =IF(B72="","",LEN(TRIM(B72))) -> 5 | D72: Easy | E72: affected with madness or insanity | G72: =IF(F72="","",LEN(F72)) | I72: =IF(H72="","",LEN(H72)) | K72: =IF(J72="","",LEN(J72))
A73: =IF(B73="","",ROW()-1) -> 72 | B73: crisp | C73: =IF(B73="","",LEN(TRIM(B73))) -> 5 | D73: Easy | E73: a thin crisp slice of potato fried in deep fat | G73: =IF(F73="","",LEN(F73)) | I73: =IF(H73="","",LEN(H73)) | K73: =IF(J73="","",LEN(J73))
A74: =IF(B74="","",ROW()-1) -> 73 | B74: cross | C74: =IF(B74="","",LEN(TRIM(B74))) -> 5 | D74: Easy | E74: travel across or pass over | G74: =IF(F74="","",LEN(F74)) | I74: =IF(H74="","",LEN(H74)) | K74: =IF(J74="","",LEN(J74))
A75: =IF(B75="","",ROW()-1) -> 74 | B75: cycle | C75: =IF(B75="","",LEN(TRIM(B75))) -> 5 | D75: Easy | E75: an interval during which a recurring sequence of events occurs | F75: Bike | G75: =IF(F75="","",LEN(F75)) -> 4 | H75: Repeating pattern | I75: =IF(H75="","",LEN(H75)) -> 17 | K75: =IF(J75="","",LEN(J75))
A76: =IF(B76="","",ROW()-1) -> 75 | B76: daily | C76: =IF(B76="","",LEN(TRIM(B76))) -> 5 | D76: Easy | E76: every day | G76: =IF(F76="","",LEN(F76)) | I76: =IF(H76="","",LEN(H76)) | K76: =IF(J76="","",LEN(J76))
A77: =IF(B77="","",ROW()-1) -> 76 | B77: delay | C77: =IF(B77="","",LEN(TRIM(B77))) -> 5 | D77: Easy | E77: cause to be slowed down or delayed | G77: =IF(F77="","",LEN(F77)) | I77: =IF(H77="","",LEN(H77)) | K77: =IF(J77="","",LEN(J77))
A78: =IF(B78="","",ROW()-1) -> 77 | B78: depth | C78: =IF(B78="","",LEN(TRIM(B78))) -> 5 | D78: Easy | E78: the extent downward or backward or inward | G78: =IF(F78="","",LEN(F78)) | I78: =IF(H78="","",LEN(H78)) | K78: =IF(J78="","",LEN(J78))
A79: =IF(B79="","",ROW()-1) -> 78 | B79: digit | C79: =IF(B79="","",LEN(TRIM(B79))) -> 5 | D79: Easy | E79: one of the elements that collectively form a system of numeration | G79: =IF(F79="","",LEN(F79)) | I79: =IF(H79="","",LEN(H79)) | K79: =IF(J79="","",LEN(J79))
A80: =IF(B80="","",ROW()-1) -> 79 | B80: dirty | C80: =IF(B80="","",LEN(TRIM(B80))) -> 5 | D80: Easy | E80: soiled or likely to soil with dirt or grime | F80: Messy | G80: =IF(F80="","",LEN(F80)) -> 5 | H80: Not clean | I80: =IF(H80="","",LEN(H80)) -> 9 | K80: =IF(J80="","",LEN(J80))
A81: =IF(B81="","",ROW()-1) -> 80 | B81: doubt | C81: =IF(B81="","",LEN(TRIM(B81))) -> 5 | D81: Easy | E81: the state of being unsure of something | F81: Uncertainty | G81: =IF(F81="","",LEN(F81)) -> 11 | H81: Not believe | I81: =IF(H81="","",LEN(H81)) -> 11 | K81: =IF(J81="","",LEN(J81))
A82: =IF(B82="","",ROW()-1) -> 81 | B82: dozen | C82: =IF(B82="","",LEN(TRIM(B82))) -> 5 | D82: Easy | E82: the cardinal number that is the sum of eleven and one | G82: =IF(F82="","",LEN(F82)) | I82: =IF(H82="","",LEN(H82)) | K82: =IF(J82="","",LEN(J82))
A83: =IF(B83="","",ROW()-1) -> 82 | B83: dream | C83: =IF(B83="","",LEN(TRIM(B83))) -> 5 | D83: Easy | E83: a series of mental images and emotions occurring during sleep | F83: Sleep vision | G83: =IF(F83="","",LEN(F83)) -> 12 | H83: Hope | I83: =IF(H83="","",LEN(H83)) -> 4 | K83: =IF(J83="","",LEN(J83))
A84: =IF(B84="","",ROW()-1) -> 83 | B84: drink | C84: =IF(B84="","",LEN(TRIM(B84))) -> 5 | D84: Easy | E84: take in liquids | G84: =IF(F84="","",LEN(F84)) | I84: =IF(H84="","",LEN(H84)) | K84: =IF(J84="","",LEN(J84))
A85: =IF(B85="","",ROW()-1) -> 84 | B85: drive | C85: =IF(B85="","",LEN(TRIM(B85))) -> 5 | D85: Easy | E85: operate or control a vehicle | F85: Steer a car | G85: =IF(F85="","",LEN(F85)) -> 11 | H85: Ambition | I85: =IF(H85="","",LEN(H85)) -> 8 | K85: =IF(J85="","",LEN(J85))
A86: =IF(B86="","",ROW()-1) -> 85 | B86: drove | C86: =IF(B86="","",LEN(TRIM(B86))) -> 5 | D86: Easy | E86: a group of animals (a herd or flock) moving together | G86: =IF(F86="","",LEN(F86)) | I86: =IF(H86="","",LEN(H86)) | K86: =IF(J86="","",LEN(J86))
A87: =IF(B87="","",ROW()-1) -> 86 | B87: early | C87: =IF(B87="","",LEN(TRIM(B87))) -> 5 | D87: Easy | E87: at or near the beginning of a period of time or course of events or before the usual or expected time | F87: Not late | G87: =IF(F87="","",LEN(F87)) -> 8 | H87: Ahead of time | I87: =IF(H87="","",LEN(H87)) -> 13 | K87: =IF(J87="","",LEN(J87))
A88: =IF(B88="","",ROW()-1) -> 87 | B88: earth | C88: =IF(B88="","",LEN(TRIM(B88))) -> 5 | D88: Easy | E88: the 3rd planet from the sun | G88: =IF(F88="","",LEN(F88)) | I88: =IF(H88="","",LEN(H88)) | K88: =IF(J88="","",LEN(J88))
A89: =IF(B89="","",ROW()-1) -> 88 | B89: eight | C89: =IF(B89="","",LEN(TRIM(B89))) -> 5 | D89: Easy | E89: being one more than seven | F89: Four plus four | G89: =IF(F89="","",LEN(F89)) -> 14 | H89: Octopus arms | I89: =IF(H89="","",LEN(H89)) -> 12 | K89: =IF(J89="","",LEN(J89))
A90: =IF(B90="","",ROW()-1) -> 89 | B90: elect | C90: =IF(B90="","",LEN(TRIM(B90))) -> 5 | D90: Easy | E90: select by a vote for an office or membership | F90: Vote in | G90: =IF(F90="","",LEN(F90)) -> 7 | H90: Choose by vote | I90: =IF(H90="","",LEN(H90)) -> 14 | K90: =IF(J90="","",LEN(J90))
A91: =IF(B91="","",ROW()-1) -> 90 | B91: empty | C91: =IF(B91="","",LEN(TRIM(B91))) -> 5 | D91: Easy | E91: make void or empty of contents | G91: =IF(F91="","",LEN(F91)) | I91: =IF(H91="","",LEN(H91)) | K91: =IF(J91="","",LEN(J91))
A92: =IF(B92="","",ROW()-1) -> 91 | B92: enemy | C92: =IF(B92="","",LEN(TRIM(B92))) -> 5 | D92: Easy | E92: an opposing military force | F92: Foe | G92: =IF(F92="","",LEN(F92)) -> 3 | H92: Opponent | I92: =IF(H92="","",LEN(H92)) -> 8 | K92: =IF(J92="","",LEN(J92))
A93: =IF(B93="","",ROW()-1) -> 92 | B93: enjoy | C93: =IF(B93="","",LEN(TRIM(B93))) -> 5 | D93: Easy | E93: derive or receive pleasure from | G93: =IF(F93="","",LEN(F93)) | I93: =IF(H93="","",LEN(H93)) | K93: =IF(J93="","",LEN(J93))
A94: =IF(B94="","",ROW()-1) -> 93 | B94: enter | C94: =IF(B94="","",LEN(TRIM(B94))) -> 5 | D94: Easy | E94: to come or go into | F94: Go in | G94: =IF(F94="","",LEN(F94)) -> 5 | H94: Keyboard key | I94: =IF(H94="","",LEN(H94)) -> 12 | K94: =IF(J94="","",LEN(J94))
A95: =IF(B95="","",ROW()-1) -> 94 | B95: entry | C95: =IF(B95="","",LEN(TRIM(B95))) -> 5 | D95: Easy | E95: an item inserted in a written record | F95: Way in | G95: =IF(F95="","",LEN(F95)) -> 6 | H95: Diary note | I95: =IF(H95="","",LEN(H95)) -> 10 | K95: =IF(J95="","",LEN(J95))
A96: =IF(B96="","",ROW()-1) -> 95 | B96: equal | C96: =IF(B96="","",LEN(TRIM(B96))) -> 5 | D96: Easy | E96: be identical or equivalent to | G96: =IF(F96="","",LEN(F96)) | I96: =IF(H96="","",LEN(H96)) | K96: =IF(J96="","",LEN(J96))
A97: =IF(B97="","",ROW()-1) -> 96 | B97: error | C97: =IF(B97="","",LEN(TRIM(B97))) -> 5 | D97: Easy | E97: a wrong action attributable to bad judgment or ignorance or inattention | F97: Mistake | G97: =IF(F97="","",LEN(F97)) -> 7 | H97: Typo, e.g. | I97: =IF(H97="","",LEN(H97)) -> 10 | K97: =IF(J97="","",LEN(J97))
A98: =IF(B98="","",ROW()-1) -> 97 | B98: event | C98: =IF(B98="","",LEN(TRIM(B98))) -> 5 | D98: Easy | E98: something that happens at a given place and time | G98: =IF(F98="","",LEN(F98)) | I98: =IF(H98="","",LEN(H98)) | K98: =IF(J98="","",LEN(J98))
A99: =IF(B99="","",ROW()-1) -> 98 | B99: every | C99: =IF(B99="","",LEN(TRIM(B99))) -> 5 | D99: Easy | E99: (used of count nouns) each and all of the members of a group considered singly and without exception | G99: =IF(F99="","",LEN(F99)) | I99: =IF(H99="","",LEN(H99)) | K99: =IF(J99="","",LEN(J99))
A100: =IF(B100="","",ROW()-1) -> 99 | B100: exact | C100: =IF(B100="","",LEN(TRIM(B100))) -> 5 | D100: Easy | E100: marked by strict and particular and complete accordance with fact | G100: =IF(F100="","",LEN(F100)) | I100: =IF(H100="","",LEN(H100)) | K100: =IF(J100="","",LEN(J100))
A101: =IF(B101="","",ROW()-1) -> 100 | B101: exist | C101: =IF(B101="","",LEN(TRIM(B101))) -> 5 | D101: Easy | E101: have an existence, be extant | G101: =IF(F101="","",LEN(F101)) | I101: =IF(H101="","",LEN(H101)) | K101: =IF(J101="","",LEN(J101))
...

Sheet 6 letters
A1: ID | B1: Word | C1: Letters | D1: Difficulty | E1: Definition | F1: Clue 1 | G1: Len | H1: Clue 2 | I1: Len | J1: Clue 3 | K1: Len | L1: Notes
A2: =IF(B2="","",ROW()-1) -> 1 | B2: accept | C2: =IF(B2="","",LEN(TRIM(B2))) -> 6 | D2: Easy | E2: consider or hold as true | G2: =IF(F2="","",LEN(F2)) | I2: =IF(H2="","",LEN(H2)) | K2: =IF(J2="","",LEN(J2))
A3: =IF(B3="","",ROW()-1) -> 2 | B3: access | C3: =IF(B3="","",LEN(TRIM(B3))) -> 6 | D3: Easy | E3: the right to enter | F3: Way in | G3: =IF(F3="","",LEN(F3)) -> 6 | H3: Right to enter | I3: =IF(H3="","",LEN(H3)) -> 14 | K3: =IF(J3="","",LEN(J3))
A4: =IF(B4="","",ROW()-1) -> 3 | B4: accord | C4: =IF(B4="","",LEN(TRIM(B4))) -> 6 | D4: Easy | E4: go together | G4: =IF(F4="","",LEN(F4)) | I4: =IF(H4="","",LEN(H4)) | K4: =IF(J4="","",LEN(J4))
A5: =IF(B5="","",ROW()-1) -> 4 | B5: across | C5: =IF(B5="","",LEN(TRIM(B5))) -> 6 | D5: Easy | E5: to the opposite side | G5: =IF(F5="","",LEN(F5)) | I5: =IF(H5="","",LEN(H5)) | K5: =IF(J5="","",LEN(J5))
A6: =IF(B6="","",ROW()-1) -> 5 | B6: action | C6: =IF(B6="","",LEN(TRIM(B6))) -> 6 | D6: Easy | E6: something done (usually as opposed to something said) | F6: Deed | G6: =IF(F6="","",LEN(F6)) -> 4 | H6: Lights, camera, ___! | I6: =IF(H6="","",LEN(H6)) -> 20 | K6: =IF(J6="","",LEN(J6))
A7: =IF(B7="","",ROW()-1) -> 6 | B7: active | C7: =IF(B7="","",LEN(TRIM(B7))) -> 6 | D7: Easy | E7: tending to become more severe or wider in scope | G7: =IF(F7="","",LEN(F7)) | I7: =IF(H7="","",LEN(H7)) | K7: =IF(J7="","",LEN(J7))
A8: =IF(B8="","",ROW()-1) -> 7 | B8: actual | C8: =IF(B8="","",LEN(TRIM(B8))) -> 6 | D8: Easy | E8: presently existing in fact and not merely potential or possible | G8: =IF(F8="","",LEN(F8)) | I8: =IF(H8="","",LEN(H8)) | K8: =IF(J8="","",LEN(J8))
A9: =IF(B9="","",ROW()-1) -> 8 | B9: adjust | C9: =IF(B9="","",LEN(TRIM(B9))) -> 6 | D9: Easy | E9: alter or regulate so as to achieve accuracy or conform to a standard | G9: =IF(F9="","",LEN(F9)) | I9: =IF(H9="","",LEN(H9)) | K9: =IF(J9="","",LEN(J9))
A10: =IF(B10="","",ROW()-1) -> 9 | B10: advice | C10: =IF(B10="","",LEN(TRIM(B10))) -> 6 | D10: Easy | E10: a proposal for an appropriate course of action | G10: =IF(F10="","",LEN(F10)) | I10: =IF(H10="","",LEN(H10)) | K10: =IF(J10="","",LEN(J10))
A11: =IF(B11="","",ROW()-1) -> 10 | B11: advise | C11: =IF(B11="","",LEN(TRIM(B11))) -> 6 | D11: Easy | E11: give advice to | G11: =IF(F11="","",LEN(F11)) | I11: =IF(H11="","",LEN(H11)) | K11: =IF(J11="","",LEN(J11))
A12: =IF(B12="","",ROW()-1) -> 11 | B12: affair | C12: =IF(B12="","",LEN(TRIM(B12))) -> 6 | D12: Easy | E12: a vaguely specified concern | G12: =IF(F12="","",LEN(F12)) | I12: =IF(H12="","",LEN(H12)) | K12: =IF(J12="","",LEN(J12))
A13: =IF(B13="","",ROW()-1) -> 12 | B13: affect | C13: =IF(B13="","",LEN(TRIM(B13))) -> 6 | D13: Easy | E13: have an effect upon | G13: =IF(F13="","",LEN(F13)) | I13: =IF(H13="","",LEN(H13)) | K13: =IF(J13="","",LEN(J13))
A14: =IF(B14="","",ROW()-1) -> 13 | B14: afford | C14: =IF(B14="","",LEN(TRIM(B14))) -> 6 | D14: Easy | E14: be able to spare or give up | G14: =IF(F14="","",LEN(F14)) | I14: =IF(H14="","",LEN(H14)) | K14: =IF(J14="","",LEN(J14))
A15: =IF(B15="","",ROW()-1) -> 14 | B15: afraid | C15: =IF(B15="","",LEN(TRIM(B15))) -> 6 | D15: Easy | E15: filled with fear or apprehension | G15: =IF(F15="","",LEN(F15)) | I15: =IF(H15="","",LEN(H15)) | K15: =IF(J15="","",LEN(J15))
A16: =IF(B16="","",ROW()-1) -> 15 | B16: agency | C16: =IF(B16="","",LEN(TRIM(B16))) -> 6 | D16: Easy | E16: an administrative unit of government | G16: =IF(F16="","",LEN(F16)) | I16: =IF(H16="","",LEN(H16)) | K16: =IF(J16="","",LEN(J16))
A17: =IF(B17="","",ROW()-1) -> 16 | B17: agreed | C17: =IF(B17="","",LEN(TRIM(B17))) -> 6 | D17: Easy | E17: united by being of the same opinion | F17: Settled | G17: =IF(F17="","",LEN(F17)) -> 7 | H17: All said yes | I17: =IF(H17="","",LEN(H17)) -> 12 | K17: =IF(J17="","",LEN(J17))
A18: =IF(B18="","",ROW()-1) -> 17 | B18: almost | C18: =IF(B18="","",LEN(TRIM(B18))) -> 6 | D18: Easy | E18: (of actions or states) slightly short of or not quite accomplished | G18: =IF(F18="","",LEN(F18)) | I18: =IF(H18="","",LEN(H18)) | K18: =IF(J18="","",LEN(J18))
A19: =IF(B19="","",ROW()-1) -> 18 | B19: always | C19: =IF(B19="","",LEN(TRIM(B19))) -> 6 | D19: Easy | E19: at all times | G19: =IF(F19="","",LEN(F19)) | I19: =IF(H19="","",LEN(H19)) | K19: =IF(J19="","",LEN(J19))
A20: =IF(B20="","",ROW()-1) -> 19 | B20: amount | C20: =IF(B20="","",LEN(TRIM(B20))) -> 6 | D20: Easy | E20: a quantity of money | G20: =IF(F20="","",LEN(F20)) | I20: =IF(H20="","",LEN(H20)) | K20: =IF(J20="","",LEN(J20))
A21: =IF(B21="","",ROW()-1) -> 20 | B21: animal | C21: =IF(B21="","",LEN(TRIM(B21))) -> 6 | D21: Easy | E21: a living organism characterized by voluntary movement | F21: Beast | G21: =IF(F21="","",LEN(F21)) -> 5 | H21: Zoo creature | I21: =IF(H21="","",LEN(H21)) -> 12 | K21: =IF(J21="","",LEN(J21))
A22: =IF(B22="","",ROW()-1) -> 21 | B22: annual | C22: =IF(B22="","",LEN(TRIM(B22))) -> 6 | D22: Easy | E22: completing its life cycle within a year | G22: =IF(F22="","",LEN(F22)) | I22: =IF(H22="","",LEN(H22)) | K22: =IF(J22="","",LEN(J22))
A23: =IF(B23="","",ROW()-1) -> 22 | B23: answer | C23: =IF(B23="","",LEN(TRIM(B23))) -> 6 | D23: Easy | E23: react verbally | G23: =IF(F23="","",LEN(F23)) | I23: =IF(H23="","",LEN(H23)) | K23: =IF(J23="","",LEN(J23))
A24: =IF(B24="","",ROW()-1) -> 23 | B24: anyway | C24: =IF(B24="","",LEN(TRIM(B24))) -> 6 | D24: Easy | E24: used to indicate that a statement explains or supports a previous statement | G24: =IF(F24="","",LEN(F24)) | I24: =IF(H24="","",LEN(H24)) | K24: =IF(J24="","",LEN(J24))
A25: =IF(B25="","",ROW()-1) -> 24 | B25: appeal | C25: =IF(B25="","",LEN(TRIM(B25))) -> 6 | D25: Easy | E25: earnest or urgent request | F25: Charm | G25: =IF(F25="","",LEN(F25)) -> 5 | H25: Ask earnestly | I25: =IF(H25="","",LEN(H25)) -> 13 | K25: =IF(J25="","",LEN(J25))
A26: =IF(B26="","",ROW()-1) -> 25 | B26: appear | C26: =IF(B26="","",LEN(TRIM(B26))) -> 6 | D26: Easy | E26: give a certain impression or have a certain outward aspect | F26: Show up | G26: =IF(F26="","",LEN(F26)) -> 7 | H26: Come into view | I26: =IF(H26="","",LEN(H26)) -> 14 | K26: =IF(J26="","",LEN(J26))
A27: =IF(B27="","",ROW()-1) -> 26 | B27: around | C27: =IF(B27="","",LEN(TRIM(B27))) -> 6 | D27: Easy | E27: in the area or vicinity | G27: =IF(F27="","",LEN(F27)) | I27: =IF(H27="","",LEN(H27)) | K27: =IF(J27="","",LEN(J27))
A28: =IF(B28="","",ROW()-1) -> 27 | B28: arrive | C28: =IF(B28="","",LEN(TRIM(B28))) -> 6 | D28: Easy | E28: reach a destination | G28: =IF(F28="","",LEN(F28)) | I28: =IF(H28="","",LEN(H28)) | K28: =IF(J28="","",LEN(J28))
A29: =IF(B29="","",ROW()-1) -> 28 | B29: artist | C29: =IF(B29="","",LEN(TRIM(B29))) -> 6 | D29: Easy | E29: a person whose creative work shows sensitivity and imagination | F29: Painter | G29: =IF(F29="","",LEN(F29)) -> 7 | H29: Creative person | I29: =IF(H29="","",LEN(H29)) -> 15 | K29: =IF(J29="","",LEN(J29))
A30: =IF(B30="","",ROW()-1) -> 29 | B30: asleep | C30: =IF(B30="","",LEN(TRIM(B30))) -> 6 | D30: Easy | E30: in a state of sleep | F30: Napping | G30: =IF(F30="","",LEN(F30)) -> 7 | H30: In dreamland | I30: =IF(H30="","",LEN(H30)) -> 12 | K30: =IF(J30="","",LEN(J30))
A31: =IF(B31="","",ROW()-1) -> 30 | B31: aspect | C31: =IF(B31="","",LEN(TRIM(B31))) -> 6 | D31: Easy | E31: a distinct feature or element in a problem | G31: =IF(F31="","",LEN(F31)) | I31: =IF(H31="","",LEN(H31)) | K31: =IF(J31="","",LEN(J31))
A32: =IF(B32="","",ROW()-1) -> 31 | B32: assume | C32: =IF(B32="","",LEN(TRIM(B32))) -> 6 | D32: Easy | E32: take to be the case or to be true | G32: =IF(F32="","",LEN(F32)) | I32: =IF(H32="","",LEN(H32)) | K32: =IF(J32="","",LEN(J32))
A33: =IF(B33="","",ROW()-1) -> 32 | B33: assure | C33: =IF(B33="","",LEN(TRIM(B33))) -> 6 | D33: Easy | E33: make certain of | F33: Promise | G33: =IF(F33="","",LEN(F33)) -> 7 | H33: Guarantee | I33: =IF(H33="","",LEN(H33)) -> 9 | K33: =IF(J33="","",LEN(J33))
A34: =IF(B34="","",ROW()-1) -> 33 | B34: attach | C34: =IF(B34="","",LEN(TRIM(B34))) -> 6 | D34: Easy | E34: cause to be attached | F34: Fasten | G34: =IF(F34="","",LEN(F34)) -> 6 | H34: Add to an email | I34: =IF(H34="","",LEN(H34)) -> 15 | K34: =IF(J34="","",LEN(J34))
A35: =IF(B35="","",ROW()-1) -> 34 | B35: attack | C35: =IF(B35="","",LEN(TRIM(B35))) -> 6 | D35: Easy | E35: (military) an offensive against an enemy (using weapons) | G35: =IF(F35="","",LEN(F35)) | I35: =IF(H35="","",LEN(H35)) | K35: =IF(J35="","",LEN(J35))
A36: =IF(B36="","",ROW()-1) -> 35 | B36: attend | C36: =IF(B36="","",LEN(TRIM(B36))) -> 6 | D36: Easy | E36: be present at (meetings, church services, university), etc. | G36: =IF(F36="","",LEN(F36)) | I36: =IF(H36="","",LEN(H36)) | K36: =IF(J36="","",LEN(J36))
A37: =IF(B37="","",ROW()-1) -> 36 | B37: author | C37: =IF(B37="","",LEN(TRIM(B37))) -> 6 | D37: Easy | E37: writes (books or stories or articles or the like) professionally (for pay) | G37: =IF(F37="","",LEN(F37)) | I37: =IF(H37="","",LEN(H37)) | K37: =IF(J37="","",LEN(J37))
A38: =IF(B38="","",ROW()-1) -> 37 | B38: autumn | C38: =IF(B38="","",LEN(TRIM(B38))) -> 6 | D38: Easy | E38: the season when the leaves fall from the trees | G38: =IF(F38="","",LEN(F38)) | I38: =IF(H38="","",LEN(H38)) | K38: =IF(J38="","",LEN(J38))
A39: =IF(B39="","",ROW()-1) -> 38 | B39: become | C39: =IF(B39="","",LEN(TRIM(B39))) -> 6 | D39: Easy | E39: enter or assume a certain state or condition | G39: =IF(F39="","",LEN(F39)) | I39: =IF(H39="","",LEN(H39)) | K39: =IF(J39="","",LEN(J39))
A40: =IF(B40="","",ROW()-1) -> 39 | B40: before | C40: =IF(B40="","",LEN(TRIM(B40))) -> 6 | D40: Easy | E40: earlier in time | G40: =IF(F40="","",LEN(F40)) | I40: =IF(H40="","",LEN(H40)) | K40: =IF(J40="","",LEN(J40))
A41: =IF(B41="","",ROW()-1) -> 40 | B41: behave | C41: =IF(B41="","",LEN(TRIM(B41))) -> 6 | D41: Easy | E41: behave in a certain manner | G41: =IF(F41="","",LEN(F41)) | I41: =IF(H41="","",LEN(H41)) | K41: =IF(J41="","",LEN(J41))
A42: =IF(B42="","",ROW()-1) -> 41 | B42: behind | C42: =IF(B42="","",LEN(TRIM(B42))) -> 6 | D42: Easy | E42: in or to or toward the rear | G42: =IF(F42="","",LEN(F42)) | I42: =IF(H42="","",LEN(H42)) | K42: =IF(J42="","",LEN(J42))
A43: =IF(B43="","",ROW()-1) -> 42 | B43: belong | C43: =IF(B43="","",LEN(TRIM(B43))) -> 6 | D43: Easy | E43: be owned by | G43: =IF(F43="","",LEN(F43)) | I43: =IF(H43="","",LEN(H43)) | K43: =IF(J43="","",LEN(J43))
A44: =IF(B44="","",ROW()-1) -> 43 | B44: better | C44: =IF(B44="","",LEN(TRIM(B44))) -> 6 | D44: Easy | E44: surpass in excellence | F44: Improved | G44: =IF(F44="","",LEN(F44)) -> 8 | H44: Superior | I44: =IF(H44="","",LEN(H44)) -> 8 | K44: =IF(J44="","",LEN(J44))
A45: =IF(B45="","",ROW()-1) -> 44 | B45: beyond | C45: =IF(B45="","",LEN(TRIM(B45))) -> 6 | D45: Easy | E45: farther along in space or time or degree | G45: =IF(F45="","",LEN(F45)) | I45: =IF(H45="","",LEN(H45)) | K45: =IF(J45="","",LEN(J45))
A46: =IF(B46="","",ROW()-1) -> 45 | B46: borrow | C46: =IF(B46="","",LEN(TRIM(B46))) -> 6 | D46: Easy | E46: get temporarily | G46: =IF(F46="","",LEN(F46)) | I46: =IF(H46="","",LEN(H46)) | K46: =IF(J46="","",LEN(J46))
A47: =IF(B47="","",ROW()-1) -> 46 | B47: bother | C47: =IF(B47="","",LEN(TRIM(B47))) -> 6 | D47: Easy | E47: take the trouble to do something | G47: =IF(F47="","",LEN(F47)) | I47: =IF(H47="","",LEN(H47)) | K47: =IF(J47="","",LEN(J47))
A48: =IF(B48="","",ROW()-1) -> 47 | B48: bottle | C48: =IF(B48="","",LEN(TRIM(B48))) -> 6 | D48: Easy | E48: a glass or plastic vessel used for storing drinks or other liquids | G48: =IF(F48="","",LEN(F48)) | I48: =IF(H48="","",LEN(H48)) | K48: =IF(J48="","",LEN(J48))
A49: =IF(B49="","",ROW()-1) -> 48 | B49: bottom | C49: =IF(B49="","",LEN(TRIM(B49))) -> 6 | D49: Easy | E49: the lower side of anything | G49: =IF(F49="","",LEN(F49)) | I49: =IF(H49="","",LEN(H49)) | K49: =IF(J49="","",LEN(J49))
A50: =IF(B50="","",ROW()-1) -> 49 | B50: branch | C50: =IF(B50="","",LEN(TRIM(B50))) -> 6 | D50: Easy | E50: a division of some larger or more complex organization | G50: =IF(F50="","",LEN(F50)) | I50: =IF(H50="","",LEN(H50)) | K50: =IF(J50="","",LEN(J50))
A51: =IF(B51="","",ROW()-1) -> 50 | B51: breach | C51: =IF(B51="","",LEN(TRIM(B51))) -> 6 | D51: Easy | E51: act in disregard of laws, rules, contracts, or promises | F51: Gap in a wall | G51: =IF(F51="","",LEN(F51)) -> 13 | H51: Rupture | I51: =IF(H51="","",LEN(H51)) -> 7 | K51: =IF(J51="","",LEN(J51))
A52: =IF(B52="","",ROW()-1) -> 51 | B52: bridge | C52: =IF(B52="","",LEN(TRIM(B52))) -> 6 | D52: Easy | E52: a structure that allows people or vehicles to cross an obstacle such as a river or canal or railway etc. | F52: River crossing | G52: =IF(F52="","",LEN(F52)) -> 14 | H52: Card game | I52: =IF(H52="","",LEN(H52)) -> 9 | K52: =IF(J52="","",LEN(J52))
A53: =IF(B53="","",ROW()-1) -> 52 | B53: bright | C53: =IF(B53="","",LEN(TRIM(B53))) -> 6 | D53: Easy | E53: emitting or reflecting light readily or in large amounts | G53: =IF(F53="","",LEN(F53)) | I53: =IF(H53="","",LEN(H53)) | K53: =IF(J53="","",LEN(J53))
A54: =IF(B54="","",ROW()-1) -> 53 | B54: broken | C54: =IF(B54="","",LEN(TRIM(B54))) -> 6 | D54: Easy | E54: physically and forcibly separated into pieces or cracked or split | G54: =IF(F54="","",LEN(F54)) | I54: =IF(H54="","",LEN(H54)) | K54: =IF(J54="","",LEN(J54))
A55: =IF(B55="","",ROW()-1) -> 54 | B55: bucket | C55: =IF(B55="","",LEN(TRIM(B55))) -> 6 | D55: Easy | E55: a roughly cylindrical vessel that is open at the top | G55: =IF(F55="","",LEN(F55)) | I55: =IF(H55="","",LEN(H55)) | K55: =IF(J55="","",LEN(J55))
A56: =IF(B56="","",ROW()-1) -> 55 | B56: budget | C56: =IF(B56="","",LEN(TRIM(B56))) -> 6 | D56: Easy | E56: a sum of money allocated for a particular purpose | G56: =IF(F56="","",LEN(F56)) | I56: =IF(H56="","",LEN(H56)) | K56: =IF(J56="","",LEN(J56))
A57: =IF(B57="","",ROW()-1) -> 56 | B57: button | C57: =IF(B57="","",LEN(TRIM(B57))) -> 6 | D57: Easy | E57: a round fastener sewn to shirts and coats etc to fit through buttonholes | G57: =IF(F57="","",LEN(F57)) | I57: =IF(H57="","",LEN(H57)) | K57: =IF(J57="","",LEN(J57))
A58: =IF(B58="","",ROW()-1) -> 57 | B58: center | C58: =IF(B58="","",LEN(TRIM(B58))) -> 6 | D58: Easy | E58: an area that is approximately central within some larger region | F58: Middle | G58: =IF(F58="","",LEN(F58)) -> 6 | H58: Midpoint | I58: =IF(H58="","",LEN(H58)) -> 8 | K58: =IF(J58="","",LEN(J58))
A59: =IF(B59="","",ROW()-1) -> 58 | B59: chance | C59: =IF(B59="","",LEN(TRIM(B59))) -> 6 | D59: Easy | E59: a possibility due to a favorable combination of circumstances | G59: =IF(F59="","",LEN(F59)) | I59: =IF(H59="","",LEN(H59)) | K59: =IF(J59="","",LEN(J59))
A60: =IF(B60="","",ROW()-1) -> 59 | B60: change | C60: =IF(B60="","",LEN(TRIM(B60))) -> 6 | D60: Easy | E60: cause to change | F60: Alter | G60: =IF(F60="","",LEN(F60)) -> 5 | H60: Coins | I60: =IF(H60="","",LEN(H60)) -> 5 | K60: =IF(J60="","",LEN(J60))
A61: =IF(B61="","",ROW()-1) -> 60 | B61: charge | C61: =IF(B61="","",LEN(TRIM(B61))) -> 6 | D61: Easy | E61: to make a rush at or sudden attack upon, as in battle | F61: Cost | G61: =IF(F61="","",LEN(F61)) -> 4 | H61: Power up a phone | I61: =IF(H61="","",LEN(H61)) -> 16 | K61: =IF(J61="","",LEN(J61))
A62: =IF(B62="","",ROW()-1) -> 61 | B62: choice | C62: =IF(B62="","",LEN(TRIM(B62))) -> 6 | D62: Easy | E62: the person or thing chosen or selected | G62: =IF(F62="","",LEN(F62)) | I62: =IF(H62="","",LEN(H62)) | K62: =IF(J62="","",LEN(J62))
A63: =IF(B63="","",ROW()-1) -> 62 | B63: choose | C63: =IF(B63="","",LEN(TRIM(B63))) -> 6 | D63: Easy | E63: pick out, select, or choose from a number of alternatives | G63: =IF(F63="","",LEN(F63)) | I63: =IF(H63="","",LEN(H63)) | K63: =IF(J63="","",LEN(J63))
A64: =IF(B64="","",ROW()-1) -> 63 | B64: circle | C64: =IF(B64="","",LEN(TRIM(B64))) -> 6 | D64: Easy | E64: ellipse in which the two axes are of equal length | G64: =IF(F64="","",LEN(F64)) | I64: =IF(H64="","",LEN(H64)) | K64: =IF(J64="","",LEN(J64))
A65: =IF(B65="","",ROW()-1) -> 64 | B65: clever | C65: =IF(B65="","",LEN(TRIM(B65))) -> 6 | D65: Easy | E65: showing self-interest and shrewdness in dealing with others | F65: Smart | G65: =IF(F65="","",LEN(F65)) -> 5 | H65: Bright | I65: =IF(H65="","",LEN(H65)) -> 6 | K65: =IF(J65="","",LEN(J65))
A66: =IF(B66="","",ROW()-1) -> 65 | B66: coffee | C66: =IF(B66="","",LEN(TRIM(B66))) -> 6 | D66: Easy | E66: a beverage consisting of an infusion of ground coffee beans | G66: =IF(F66="","",LEN(F66)) | I66: =IF(H66="","",LEN(H66)) | K66: =IF(J66="","",LEN(J66))
A67: =IF(B67="","",ROW()-1) -> 66 | B67: column | C67: =IF(B67="","",LEN(TRIM(B67))) -> 6 | D67: Easy | E67: a line of units following one after another | G67: =IF(F67="","",LEN(F67)) | I67: =IF(H67="","",LEN(H67)) | K67: =IF(J67="","",LEN(J67))
A68: =IF(B68="","",ROW()-1) -> 67 | B68: coming | C68: =IF(B68="","",LEN(TRIM(B68))) -> 6 | D68: Easy | E68: the act of drawing spatially closer to something | G68: =IF(F68="","",LEN(F68)) | I68: =IF(H68="","",LEN(H68)) | K68: =IF(J68="","",LEN(J68))
A69: =IF(B69="","",ROW()-1) -> 68 | B69: common | C69: =IF(B69="","",LEN(TRIM(B69))) -> 6 | D69: Easy | E69: belonging to or participated in by a community as a whole | G69: =IF(F69="","",LEN(F69)) | I69: =IF(H69="","",LEN(H69)) | K69: =IF(J69="","",LEN(J69))
A70: =IF(B70="","",ROW()-1) -> 69 | B70: corner | C70: =IF(B70="","",LEN(TRIM(B70))) -> 6 | D70: Easy | E70: a place off to the side of an area | G70: =IF(F70="","",LEN(F70)) | I70: =IF(H70="","",LEN(H70)) | K70: =IF(J70="","",LEN(J70))
A71: =IF(B71="","",ROW()-1) -> 70 | B71: county | C71: =IF(B71="","",LEN(TRIM(B71))) -> 6 | D71: Easy | E71: (United Kingdom) a region created by territorial division for the purpose of local government | G71: =IF(F71="","",LEN(F71)) | I71: =IF(H71="","",LEN(H71)) | K71: =IF(J71="","",LEN(J71))
A72: =IF(B72="","",ROW()-1) -> 71 | B72: couple | C72: =IF(B72="","",LEN(TRIM(B72))) -> 6 | D72: Easy | E72: a pair who associate with one another | G72: =IF(F72="","",LEN(F72)) | I72: =IF(H72="","",LEN(H72)) | K72: =IF(J72="","",LEN(J72))
A73: =IF(B73="","",ROW()-1) -> 72 | B73: course | C73: =IF(B73="","",LEN(TRIM(B73))) -> 6 | D73: Easy | E73: education imparted in a series of lessons or meetings | G73: =IF(F73="","",LEN(F73)) | I73: =IF(H73="","",LEN(H73)) | K73: =IF(J73="","",LEN(J73))
A74: =IF(B74="","",ROW()-1) -> 73 | B74: create | C74: =IF(B74="","",LEN(TRIM(B74))) -> 6 | D74: Easy | E74: make or cause to be or to become | F74: Make | G74: =IF(F74="","",LEN(F74)) -> 4 | H74: Bring about | I74: =IF(H74="","",LEN(H74)) -> 11 | K74: =IF(J74="","",LEN(J74))
A75: =IF(B75="","",ROW()-1) -> 74 | B75: credit | C75: =IF(B75="","",LEN(TRIM(B75))) -> 6 | D75: Easy | E75: approval | G75: =IF(F75="","",LEN(F75)) | I75: =IF(H75="","",LEN(H75)) | K75: =IF(J75="","",LEN(J75))
A76: =IF(B76="","",ROW()-1) -> 75 | B76: crisis | C76: =IF(B76="","",LEN(TRIM(B76))) -> 6 | D76: Easy | E76: an unstable situation of extreme danger or difficulty | G76: =IF(F76="","",LEN(F76)) | I76: =IF(H76="","",LEN(H76)) | K76: =IF(J76="","",LEN(J76))
A77: =IF(B77="","",ROW()-1) -> 76 | B77: damage | C77: =IF(B77="","",LEN(TRIM(B77))) -> 6 | D77: Easy | E77: the occurrence of a change for the worse | G77: =IF(F77="","",LEN(F77)) | I77: =IF(H77="","",LEN(H77)) | K77: =IF(J77="","",LEN(J77))
A78: =IF(B78="","",ROW()-1) -> 77 | B78: danger | C78: =IF(B78="","",LEN(TRIM(B78))) -> 6 | D78: Easy | E78: the condition of being susceptible to harm or injury | F78: Peril | G78: =IF(F78="","",LEN(F78)) -> 5 | H78: Risk | I78: =IF(H78="","",LEN(H78)) -> 4 | K78: =IF(J78="","",LEN(J78))
A79: =IF(B79="","",ROW()-1) -> 78 | B79: debate | C79: =IF(B79="","",LEN(TRIM(B79))) -> 6 | D79: Easy | E79: argue with one another | G79: =IF(F79="","",LEN(F79)) | I79: =IF(H79="","",LEN(H79)) | K79: =IF(J79="","",LEN(J79))
A80: =IF(B80="","",ROW()-1) -> 79 | B80: decade | C80: =IF(B80="","",LEN(TRIM(B80))) -> 6 | D80: Easy | E80: a period of 10 years | G80: =IF(F80="","",LEN(F80)) | I80: =IF(H80="","",LEN(H80)) | K80: =IF(J80="","",LEN(J80))
A81: =IF(B81="","",ROW()-1) -> 80 | B81: decent | C81: =IF(B81="","",LEN(TRIM(B81))) -> 6 | D81: Easy | E81: socially or conventionally correct | G81: =IF(F81="","",LEN(F81)) | I81: =IF(H81="","",LEN(H81)) | K81: =IF(J81="","",LEN(J81))
A82: =IF(B82="","",ROW()-1) -> 81 | B82: decide | C82: =IF(B82="","",LEN(TRIM(B82))) -> 6 | D82: Easy | E82: reach, make, or come to a decision about something | F82: Make up your mind | G82: =IF(F82="","",LEN(F82)) -> 17 | H82: Choose | I82: =IF(H82="","",LEN(H82)) -> 6 | K82: =IF(J82="","",LEN(J82))
A83: =IF(B83="","",ROW()-1) -> 82 | B83: deeply | C83: =IF(B83="","",LEN(TRIM(B83))) -> 6 | D83: Easy | E83: to a great depth psychologically | F83: Profoundly | G83: =IF(F83="","",LEN(F83)) -> 10 | H83: Very much | I83: =IF(H83="","",LEN(H83)) -> 9 | K83: =IF(J83="","",LEN(J83))
A84: =IF(B84="","",ROW()-1) -> 83 | B84: define | C84: =IF(B84="","",LEN(TRIM(B84))) -> 6 | D84: Easy | E84: determine the essential quality of | F84: Explain meaning | G84: =IF(F84="","",LEN(F84)) -> 15 | H84: Describe exactly | I84: =IF(H84="","",LEN(H84)) -> 16 | K84: =IF(J84="","",LEN(J84))
A85: =IF(B85="","",ROW()-1) -> 84 | B85: degree | C85: =IF(B85="","",LEN(TRIM(B85))) -> 6 | D85: Easy | E85: a position on a scale of intensity or amount or quality | F85: Unit of heat | G85: =IF(F85="","",LEN(F85)) -> 12 | H85: College award | I85: =IF(H85="","",LEN(H85)) -> 13 | K85: =IF(J85="","",LEN(J85))
A86: =IF(B86="","",ROW()-1) -> 85 | B86: delete | C86: =IF(B86="","",LEN(TRIM(B86))) -> 6 | D86: Easy | E86: remove or make invisible | F86: Erase | G86: =IF(F86="","",LEN(F86)) -> 5 | H86: Remove text | I86: =IF(H86="","",LEN(H86)) -> 11 | K86: =IF(J86="","",LEN(J86))
A87: =IF(B87="","",ROW()-1) -> 86 | B87: demand | C87: =IF(B87="","",LEN(TRIM(B87))) -> 6 | D87: Easy | E87: an urgent or peremptory request | G87: =IF(F87="","",LEN(F87)) | I87: =IF(H87="","",LEN(H87)) | K87: =IF(J87="","",LEN(J87))
A88: =IF(B88="","",ROW()-1) -> 87 | B88: depend | C88: =IF(B88="","",LEN(TRIM(B88))) -> 6 | D88: Easy | E88: be contingent upon (something that is elided) | F88: Rely | G88: =IF(F88="","",LEN(F88)) -> 4 | H88: Count (on) | I88: =IF(H88="","",LEN(H88)) -> 10 | K88: =IF(J88="","",LEN(J88))
A89: =IF(B89="","",ROW()-1) -> 88 | B89: design | C89: =IF(B89="","",LEN(TRIM(B89))) -> 6 | D89: Easy | E89: the act of working out the form of something (as by making a sketch or outline or plan) | G89: =IF(F89="","",LEN(F89)) | I89: =IF(H89="","",LEN(H89)) | K89: =IF(J89="","",LEN(J89))
A90: =IF(B90="","",ROW()-1) -> 89 | B90: desire | C90: =IF(B90="","",LEN(TRIM(B90))) -> 6 | D90: Easy | E90: the feeling that accompanies an unsatisfied state | G90: =IF(F90="","",LEN(F90)) | I90: =IF(H90="","",LEN(H90)) | K90: =IF(J90="","",LEN(J90))
A91: =IF(B91="","",ROW()-1) -> 90 | B91: detail | C91: =IF(B91="","",LEN(TRIM(B91))) -> 6 | D91: Easy | E91: an isolated fact that is considered separately from the whole | G91: =IF(F91="","",LEN(F91)) | I91: =IF(H91="","",LEN(H91)) | K91: =IF(J91="","",LEN(J91))
A92: =IF(B92="","",ROW()-1) -> 91 | B92: detect | C92: =IF(B92="","",LEN(TRIM(B92))) -> 6 | D92: Easy | E92: discover or determine the existence, presence, or fact of | G92: =IF(F92="","",LEN(F92)) | I92: =IF(H92="","",LEN(H92)) | K92: =IF(J92="","",LEN(J92))
A93: =IF(B93="","",ROW()-1) -> 92 | B93: device | C93: =IF(B93="","",LEN(TRIM(B93))) -> 6 | D93: Easy | E93: an instrumentality invented for a particular purpose | G93: =IF(F93="","",LEN(F93)) | I93: =IF(H93="","",LEN(H93)) | K93: =IF(J93="","",LEN(J93))
A94: =IF(B94="","",ROW()-1) -> 93 | B94: devote | C94: =IF(B94="","",LEN(TRIM(B94))) -> 6 | D94: Easy | E94: give entirely to a specific person, activity, or cause | F94: Dedicate | G94: =IF(F94="","",LEN(F94)) -> 8 | H94: Commit | I94: =IF(H94="","",LEN(H94)) -> 6 | K94: =IF(J94="","",LEN(J94))
A95: =IF(B95="","",ROW()-1) -> 94 | B95: differ | C95: =IF(B95="","",LEN(TRIM(B95))) -> 6 | D95: Easy | E95: be different | G95: =IF(F95="","",LEN(F95)) | I95: =IF(H95="","",LEN(H95)) | K95: =IF(J95="","",LEN(J95))
A96: =IF(B96="","",ROW()-1) -> 95 | B96: dinner | C96: =IF(B96="","",LEN(TRIM(B96))) -> 6 | D96: Easy | E96: the main meal of the day served in the evening or at midday | G96: =IF(F96="","",LEN(F96)) | I96: =IF(H96="","",LEN(H96)) | K96: =IF(J96="","",LEN(J96))
A97: =IF(B97="","",ROW()-1) -> 96 | B97: direct | C97: =IF(B97="","",LEN(TRIM(B97))) -> 6 | D97: Easy | E97: command with authority | G97: =IF(F97="","",LEN(F97)) | I97: =IF(H97="","",LEN(H97)) | K97: =IF(J97="","",LEN(J97))
A98: =IF(B98="","",ROW()-1) -> 97 | B98: divide | C98: =IF(B98="","",LEN(TRIM(B98))) -> 6 | D98: Easy | E98: separate into parts or portions | G98: =IF(F98="","",LEN(F98)) | I98: =IF(H98="","",LEN(H98)) | K98: =IF(J98="","",LEN(J98))
A99: =IF(B99="","",ROW()-1) -> 98 | B99: dollar | C99: =IF(B99="","",LEN(TRIM(B99))) -> 6 | D99: Easy | E99: the basic monetary unit in many countries | F99: US money | G99: =IF(F99="","",LEN(F99)) -> 8 | H99: Buck | I99: =IF(H99="","",LEN(H99)) -> 4 | K99: =IF(J99="","",LEN(J99))
A100: =IF(B100="","",ROW()-1) -> 99 | B100: double | C100: =IF(B100="","",LEN(TRIM(B100))) -> 6 | D100: Easy | E100: increase twofold | G100: =IF(F100="","",LEN(F100)) | I100: =IF(H100="","",LEN(H100)) | K100: =IF(J100="","",LEN(J100))
...

Sheet 7 letters
A1: ID | B1: Word | C1: Letters | D1: Difficulty | E1: Definition | F1: Clue 1 | G1: Len | H1: Clue 2 | I1: Len | J1: Clue 3 | K1: Len | L1: Notes
A2: =IF(B2="","",ROW()-1) -> 1 | B2: ability | C2: =IF(B2="","",LEN(TRIM(B2))) -> 7 | D2: Easy | E2: the quality of being able to perform | G2: =IF(F2="","",LEN(F2)) | I2: =IF(H2="","",LEN(H2)) | K2: =IF(J2="","",LEN(J2))
A3: =IF(B3="","",ROW()-1) -> 2 | B3: absence | C3: =IF(B3="","",LEN(TRIM(B3))) -> 7 | D3: Easy | E3: the state of being absent | G3: =IF(F3="","",LEN(F3)) | I3: =IF(H3="","",LEN(H3)) | K3: =IF(J3="","",LEN(J3))
A4: =IF(B4="","",ROW()-1) -> 3 | B4: account | C4: =IF(B4="","",LEN(TRIM(B4))) -> 7 | D4: Easy | E4: a record or narrative description of past events | G4: =IF(F4="","",LEN(F4)) | I4: =IF(H4="","",LEN(H4)) | K4: =IF(J4="","",LEN(J4))
A5: =IF(B5="","",ROW()-1) -> 4 | B5: achieve | C5: =IF(B5="","",LEN(TRIM(B5))) -> 7 | D5: Easy | E5: to gain with effort | G5: =IF(F5="","",LEN(F5)) | I5: =IF(H5="","",LEN(H5)) | K5: =IF(J5="","",LEN(J5))
A6: =IF(B6="","",ROW()-1) -> 5 | B6: acquire | C6: =IF(B6="","",LEN(TRIM(B6))) -> 7 | D6: Easy | E6: come into the possession of something concrete or abstract | G6: =IF(F6="","",LEN(F6)) | I6: =IF(H6="","",LEN(H6)) | K6: =IF(J6="","",LEN(J6))
A7: =IF(B7="","",ROW()-1) -> 6 | B7: address | C7: =IF(B7="","",LEN(TRIM(B7))) -> 7 | D7: Easy | E7: speak to | G7: =IF(F7="","",LEN(F7)) | I7: =IF(H7="","",LEN(H7)) | K7: =IF(J7="","",LEN(J7))
A8: =IF(B8="","",ROW()-1) -> 7 | B8: adopted | C8: =IF(B8="","",LEN(TRIM(B8))) -> 7 | D8: Easy | E8: acquired as your own by free choice | G8: =IF(F8="","",LEN(F8)) | I8: =IF(H8="","",LEN(H8)) | K8: =IF(J8="","",LEN(J8))
A9: =IF(B9="","",ROW()-1) -> 8 | B9: advance | C9: =IF(B9="","",LEN(TRIM(B9))) -> 7 | D9: Easy | E9: move forward, also in the metaphorical sense | G9: =IF(F9="","",LEN(F9)) | I9: =IF(H9="","",LEN(H9)) | K9: =IF(J9="","",LEN(J9))
A10: =IF(B10="","",ROW()-1) -> 9 | B10: already | C10: =IF(B10="","",LEN(TRIM(B10))) -> 7 | D10: Easy | E10: prior to a specified or implied time | G10: =IF(F10="","",LEN(F10)) | I10: =IF(H10="","",LEN(H10)) | K10: =IF(J10="","",LEN(J10))
A11: =IF(B11="","",ROW()-1) -> 10 | B11: altered | C11: =IF(B11="","",LEN(TRIM(B11))) -> 7 | D11: Easy | E11: changed in form or character without becoming something else | G11: =IF(F11="","",LEN(F11)) | I11: =IF(H11="","",LEN(H11)) | K11: =IF(J11="","",LEN(J11))
A12: =IF(B12="","",ROW()-1) -> 11 | B12: ancient | C12: =IF(B12="","",LEN(TRIM(B12))) -> 7 | D12: Easy | E12: belonging to times long past especially of the historical period before the fall of the Western Roman Empire | G12: =IF(F12="","",LEN(F12)) | I12: =IF(H12="","",LEN(H12)) | K12: =IF(J12="","",LEN(J12))
A13: =IF(B13="","",ROW()-1) -> 12 | B13: another | C13: =IF(B13="","",LEN(TRIM(B13))) -> 7 | D13: Easy | E13: any of various alternatives | G13: =IF(F13="","",LEN(F13)) | I13: =IF(H13="","",LEN(H13)) | K13: =IF(J13="","",LEN(J13))
... A3002: =IF(B3002="","",ROW()-1) -> 3001 | B3002: yardage | C3002: =IF(B3002="","",LEN(TRIM(B3002))) -> 7 | D3002: Rare | E3002: distance measured in the aggregate number of yards | G3002: =IF(F3002="","",LEN(F3002)) | I3002: =IF(H3002="","",LEN(H3002)) | K3002: =IF(J3002="","",LEN(J3002))
A3003: =IF(B3003="","",ROW()-1) | C3003: =IF(B3003="","",LEN(TRIM(B3003))) | G3003: =IF(F3003="","",LEN(F3003)) | I3003: =IF(H3003="","",LEN(H3003)) | K3003: =IF(J3003="","",LEN(J3003))
A3004: =IF(B3004="","",ROW()-1) | C3004: =IF(B3004="","",LEN(TRIM(B3004))) | G3004: =IF(F3004="","",LEN(F3004)) | I3004: =IF(H3004="","",LEN(H3004)) | K3004: =IF(J3004="","",LEN(J3004))
A3005: =IF(B3005="","",ROW()-1) | C3005: =IF(B3005="","",LEN(TRIM(B3005))) | G3005: =IF(F3005="","",LEN(F3005)) | I3005: =IF(H3005="","",LEN(H3005)) | K3005: =IF(J3005="","",LEN(J3005))
A3006: =IF(B3006="","",ROW()-1) | C3006: =IF(B3006="","",LEN(TRIM(B3006))) | G3006: =IF(F3006="","",LEN(F3006)) | I3006: =IF(H3006="","",LEN(H3006)) | K3006: =IF(J3006="","",LEN(J3006))
A3007: =IF(B3007="","",ROW()-1) | C3007: =IF(B3007="","",LEN(TRIM(B3007))) | G3007: =IF(F3007="","",LEN(F3007)) | I3007: =IF(H3007="","",LEN(H3007)) | K3007: =IF(J3007="","",LEN(J3007))
A3008: =IF(B3008="","",ROW()-1) | C3008: =IF(B3008="","",LEN(TRIM(B3008))) | G3008: =IF(F3008="","",LEN(F3008)) | I3008: =IF(H3008="","",LEN(H3008)) | K3008: =IF(J3008="","",LEN(J3008))
A3009: =IF(B3009="","",ROW()-1) | C3009: =IF(B3009="","",LEN(TRIM(B3009))) | G3009: =IF(F3009="","",LEN(F3009)) | I3009: =IF(H3009="","",LEN(H3009)) | K3009: =IF(J3009="","",LEN(J3009))
A3010: =IF(B3010="","",ROW()-1) | C3010: =IF(B3010="","",LEN(TRIM(B3010))) | G3010: =IF(F3010="","",LEN(F3010)) | I3010: =IF(H3010="","",LEN(H3010)) | K3010: =IF(J3010="","",LEN(J3010))
A3011: =IF(B3011="","",ROW()-1) | C3011: =IF(B3011="","",LEN(TRIM(B3011))) | G3011: =IF(F3011="","",LEN(F3011)) | I3011: =IF(H3011="","",LEN(H3011)) | K3011: =IF(J3011="","",LEN(J3011))
A3012: =IF(B3012="","",ROW()-1) | C3012: =IF(B3012="","",LEN(TRIM(B3012))) | G3012: =IF(F3012="","",LEN(F3012)) | I3012: =IF(H3012="","",LEN(H3012)) | K3012: =IF(J3012="","",LEN(J3012))
A3013: =IF(B3013="","",ROW()-1) | C3013: =IF(B3013="","",LEN(TRIM(B3013))) | G3013: =IF(F3013="","",LEN(F3013)) | I3013: =IF(H3013="","",LEN(H3013)) | K3013: =IF(J3013="","",LEN(J3013))
A3014: =IF(B3014="","",ROW()-1) | C3014: =IF(B3014="","",LEN(TRIM(B3014))) | G3014: =IF(F3014="","",LEN(F3014)) | I3014: =IF(H3014="","",LEN(H3014)) | K3014: =IF(J3014="","",LEN(J3014))
... A3502: =IF(B3502="","",ROW()-1) | C3502: =IF(B3502="","",LEN(TRIM(B3502))) | G3502: =IF(F3502="","",LEN(F3502)) | I3502: =IF(H3502="","",LEN(H3502)) | K3502: =IF(J3502="","",LEN(J3502))

Sheet 8 letters
A1: ID | B1: Word | C1: Letters | D1: Difficulty | E1: Definition | F1: Clue 1 | G1: Len | H1: Clue 2 | I1: Len | J1: Clue 3 | K1: Len | L1: Notes
A2: =IF(B2="","",ROW()-1) -> 1 | B2: absolute | C2: =IF(B2="","",LEN(TRIM(B2))) -> 8 | D2: Easy | E2: perfect or complete or pure | G2: =IF(F2="","",LEN(F2)) | I2: =IF(H2="","",LEN(H2)) | K2: =IF(J2="","",LEN(J2))
A3: =IF(B3="","",ROW()-1) -> 2 | B3: academic | C3: =IF(B3="","",LEN(TRIM(B3))) -> 8 | D3: Easy | E3: associated with academia or an academy | G3: =IF(F3="","",LEN(F3)) | I3: =IF(H3="","",LEN(H3)) | K3: =IF(J3="","",LEN(J3))
A4: =IF(B4="","",ROW()-1) -> 3 | B4: accepted | C4: =IF(B4="","",LEN(TRIM(B4))) -> 8 | D4: Easy | E4: generally approved or compelling recognition | G4: =IF(F4="","",LEN(F4)) | I4: =IF(H4="","",LEN(H4)) | K4: =IF(J4="","",LEN(J4))
A5: =IF(B5="","",ROW()-1) -> 4 | B5: accident | C5: =IF(B5="","",LEN(TRIM(B5))) -> 8 | D5: Easy | E5: an unfortunate mishap | G5: =IF(F5="","",LEN(F5)) | I5: =IF(H5="","",LEN(H5)) | K5: =IF(J5="","",LEN(J5))
A6: =IF(B6="","",ROW()-1) -> 5 | B6: accuracy | C6: =IF(B6="","",LEN(TRIM(B6))) -> 8 | D6: Easy | E6: the quality of being near to the true value | G6: =IF(F6="","",LEN(F6)) | I6: =IF(H6="","",LEN(H6)) | K6: =IF(J6="","",LEN(J6))
A7: =IF(B7="","",ROW()-1) -> 6 | B7: accurate | C7: =IF(B7="","",LEN(TRIM(B7))) -> 8 | D7: Easy | E7: conforming exactly or almost exactly to fact or to a standard or performing with total accuracy | G7: =IF(F7="","",LEN(F7)) | I7: =IF(H7="","",LEN(H7)) | K7: =IF(J7="","",LEN(J7))
A8: =IF(B8="","",ROW()-1) -> 7 | B8: acquired | C8: =IF(B8="","",LEN(TRIM(B8))) -> 8 | D8: Easy | E8: gotten through environmental forces | G8: =IF(F8="","",LEN(F8)) | I8: =IF(H8="","",LEN(H8)) | K8: =IF(J8="","",LEN(J8))
A9: =IF(B9="","",ROW()-1) -> 8 | B9: activity | C9: =IF(B9="","",LEN(TRIM(B9))) -> 8 | D9: Easy | E9: any specific behavior | G9: =IF(F9="","",LEN(F9)) | I9: =IF(H9="","",LEN(H9)) | K9: =IF(J9="","",LEN(J9))
A10: =IF(B10="","",ROW()-1) -> 9 | B10: actually | C10: =IF(B10="","",LEN(TRIM(B10))) -> 8 | D10: Easy | E10: in actual fact | G10: =IF(F10="","",LEN(F10)) | I10: =IF(H10="","",LEN(H10)) | K10: =IF(J10="","",LEN(J10))
A11: =IF(B11="","",ROW()-1) -> 10 | B11: addition | C11: =IF(B11="","",LEN(TRIM(B11))) -> 8 | D11: Easy | E11: a component that is added to something to improve it | G11: =IF(F11="","",LEN(F11)) | I11: =IF(H11="","",LEN(H11)) | K11: =IF(J11="","",LEN(J11))
A12: =IF(B12="","",ROW()-1) -> 11 | B12: adequate | C12: =IF(B12="","",LEN(TRIM(B12))) -> 8 | D12: Easy | E12: having the requisite qualities or resources to meet a task | G12: =IF(F12="","",LEN(F12)) | I12: =IF(H12="","",LEN(H12)) | K12: =IF(J12="","",LEN(J12))
A13: =IF(B13="","",ROW()-1) -> 12 | B13: affected | C13: =IF(B13="","",LEN(TRIM(B13))) -> 8 | D13: Easy | E13: acted upon | G13: =IF(F13="","",LEN(F13)) | I13: =IF(H13="","",LEN(H13)) | K13: =IF(J13="","",LEN(J13))
... A2846: =IF(B2846="","",ROW()-1) -> 2845 | B2846: zeppelin | C2846: =IF(B2846="","",LEN(TRIM(B2846))) -> 8 | D2846: Rare | E2846: German inventor who designed and built the first rigid motorized dirigible (1838-1917) | G2846: =IF(F2846="","",LEN(F2846)) | I2846: =IF(H2846="","",LEN(H2846)) | K2846: =IF(J2846="","",LEN(J2846))
A2847: =IF(B2847="","",ROW()-1) | C2847: =IF(B2847="","",LEN(TRIM(B2847))) | G2847: =IF(F2847="","",LEN(F2847)) | I2847: =IF(H2847="","",LEN(H2847)) | K2847: =IF(J2847="","",LEN(J2847))
A2848: =IF(B2848="","",ROW()-1) | C2848: =IF(B2848="","",LEN(TRIM(B2848))) | G2848: =IF(F2848="","",LEN(F2848)) | I2848: =IF(H2848="","",LEN(H2848)) | K2848: =IF(J2848="","",LEN(J2848))
A2849: =IF(B2849="","",ROW()-1) | C2849: =IF(B2849="","",LEN(TRIM(B2849))) | G2849: =IF(F2849="","",LEN(F2849)) | I2849: =IF(H2849="","",LEN(H2849)) | K2849: =IF(J2849="","",LEN(J2849))
A2850: =IF(B2850="","",ROW()-1) | C2850: =IF(B2850="","",LEN(TRIM(B2850))) | G2850: =IF(F2850="","",LEN(F2850)) | I2850: =IF(H2850="","",LEN(H2850)) | K2850: =IF(J2850="","",LEN(J2850))
A2851: =IF(B2851="","",ROW()-1) | C2851: =IF(B2851="","",LEN(TRIM(B2851))) | G2851: =IF(F2851="","",LEN(F2851)) | I2851: =IF(H2851="","",LEN(H2851)) | K2851: =IF(J2851="","",LEN(J2851))
A2852: =IF(B2852="","",ROW()-1) | C2852: =IF(B2852="","",LEN(TRIM(B2852))) | G2852: =IF(F2852="","",LEN(F2852)) | I2852: =IF(H2852="","",LEN(H2852)) | K2852: =IF(J2852="","",LEN(J2852))
A2853: =IF(B2853="","",ROW()-1) | C2853: =IF(B2853="","",LEN(TRIM(B2853))) | G2853: =IF(F2853="","",LEN(F2853)) | I2853: =IF(H2853="","",LEN(H2853)) | K2853: =IF(J2853="","",LEN(J2853))
A2854: =IF(B2854="","",ROW()-1) | C2854: =IF(B2854="","",LEN(TRIM(B2854))) | G2854: =IF(F2854="","",LEN(F2854)) | I2854: =IF(H2854="","",LEN(H2854)) | K2854: =IF(J2854="","",LEN(J2854))
A2855: =IF(B2855="","",ROW()-1) | C2855: =IF(B2855="","",LEN(TRIM(B2855))) | G2855: =IF(F2855="","",LEN(F2855)) | I2855: =IF(H2855="","",LEN(H2855)) | K2855: =IF(J2855="","",LEN(J2855))
A2856: =IF(B2856="","",ROW()-1) | C2856: =IF(B2856="","",LEN(TRIM(B2856))) | G2856: =IF(F2856="","",LEN(F2856)) | I2856: =IF(H2856="","",LEN(H2856)) | K2856: =IF(J2856="","",LEN(J2856))
A2857: =IF(B2857="","",ROW()-1) | C2857: =IF(B2857="","",LEN(TRIM(B2857))) | G2857: =IF(F2857="","",LEN(F2857)) | I2857: =IF(H2857="","",LEN(H2857)) | K2857: =IF(J2857="","",LEN(J2857))
A2858: =IF(B2858="","",ROW()-1) | C2858: =IF(B2858="","",LEN(TRIM(B2858))) | G2858: =IF(F2858="","",LEN(F2858)) | I2858: =IF(H2858="","",LEN(H2858)) | K2858: =IF(J2858="","",LEN(J2858))
... A3346: =IF(B3346="","",ROW()-1) | C3346: =IF(B3346="","",LEN(TRIM(B3346))) | G3346: =IF(F3346="","",LEN(F3346)) | I3346: =IF(H3346="","",LEN(H3346)) | K3346: =IF(J3346="","",LEN(J3346))
